Workbook

Sheet Dermatoses Bulleuses CNHU HKM
A1: _id | B1: start | C1: end | D1: today | E1: Âge (en mois) | F1: age_years_calc | G1: Sexe | H1: Profession | I1: Date de consultation | J1: Délai de consultation (en jours) | K1: Notion de prise médicamenteuse | L1: Préciser le ou les médicament(s) | M1: Type d'atteinte | N1: Surface corporelle atteinte | O1: Signes associés | P1: Préciser l'autre signe | Q1: Catégorie de la dermatose | R1: Dermatose Auto-immune | S1: Dermatose Infectieuse | T1: Toxidermie | U1: Dermatose Immunoallergique | V1: Préciser l'autre diagnostic
A2: 715501306 | B2: 46116.48 | C2: 46116.484 | D2: 46116 | E2: 1 | F2: 0.1 | G2: Homme | H2: Aucune | I2: 42397 | J2: 9 | K2: Non | M2: Cutanée seule | N2: 15 | O2: Autre | P2: Aucun | Q2: Infectieuse | S2: Épidermolyse staphylococcique
A3: 715512334 | B3: 46116.484 | C3: 46116.497 | D3: 46116 | E3: 468 | F3: 39 | G3: Femme | H3: Ménagère | I3: 42418 | J3: 14 | K3: Oui | L3: Amoxicilline | M3: Cutanée seule | N3: 5 | O3: Prurit | Q3: Toxidermie | T3: EPF Bulleux
A4: 715636712 | B4: 46116.497 | C4: 46116.632 | D4: 46116 | E4: 324 | F4: 27 | G4: Homme | H4: Sociologue | I4: 42451 | J4: 7 | K4: Oui | L4: Doxycycline CP,, nitrofurantoin cp | M4: Cutanée et muqueuse | N4: 3 | O4: Prurit | Q4: Toxidermie | T4: EPF Bulleux
A5: 715641743 | B5: 46116.632 | C5: 46116.637 | D5: 46116 | E5: 552 | F5: 46 | G5: Homme | H5: Commerçant | I5: 42388 | J5: 90 | K5: Non | M5: Cutanée seule | N5: 6 | O5: Prurit | Q5: Auto-immune | R5: Dermatose à IgA linéaire
A6: 718547936 | B6: 46119.907 | C6: 46119.952 | D6: 46119 | E6: 67 | F6: 5.6 | G6: Femme | H6: Enseignante | I6: 42929 | J6: 31 | K6: Oui | L6: Aerius cp,flagyl cp,lincocyne cp | M6: Cutanée seule | N6: 30 | O6: Autre | P6: Aucun | Q6: Auto-immune | R6: Pemphigoïde bulleuse
A7: 718789179 | B7: 46119.962 | C7: 46120.246 | D7: 46119 | E7: 552 | F7: 46 | G7: Femme | H7: Vendeuse | I7: 42765 | J7: 3 | K7: Oui | L7: Cotrimoxazole, ibuprofene, quinine, paracetamol, metronidazole | M7: Cutanée seule | N7: 45 | O7: Autre | P7: Aucun | Q7: Toxidermie | T7: Autre à préciser... | V7: Érythème pigmenté fixe
A8: 718806158 | B8: 46120.246 | C8: 46120.258 | D8: 46120 | E8: 516 | F8: 43 | G8: Homme | H8: Cultivateur | I8: 42744 | J8: 63 | K8: Oui | L8: Griseofilvine cp, polaramine cp, cetimizine cp, deslora denk, atarax 25mg | M8: Cutanée seule | N8: 80 | O8: Prurit Fièvre | Q8: Toxidermie | T8: Autre à préciser... | V8: Erytrodermie
A9: 718947052 | B9: 46120.258 | C9: 46120.345 | D9: 46120 | E9: 456 | F9: 38 | G9: Femme | H9: Coiffeuse | I9: 42740 | J9: 6 | K9: Non | M9: Cutanée seule | N9: 50 | O9: Autre | P9: Aucun | Q9: Toxidermie | T9: EPF Bulleux
A10: 719403589 | B10: 46120.345 | C10: 46120.661 | D10: 46120 | E10: 480 | F10: 40 | G10: Femme | H10: Vendeuse | I10: 42793 | J10: 2310 | K10: Oui | L10: Vitafer sirop, forcan 150mg, lorhist cp | M10: Cutanée et muqueuse | N10: 60 | O10: Prurit | Q10: Toxidermie | T10: Autre à préciser... | V10: Epidermolyse bulleuse acquise
A11: 719426805 | B11: 46120.661 | C11: 46120.676 | D11: 46120 | E11: 288 | F11: 24 | G11: Femme | H11: Agent commercial | I11: 42775 | J11: 93 | K11: Non | M11: Cutanée et muqueuse | N11: 2 | O11: Prurit | Q11: Infectieuse | S11: Autre à préciser... | V11: Érythème pigmenté fixe
A12: 722449196 | B12: 46120.676 | C12: 46123.962 | D12: 46120 | E12: 288 | F12: 24 | G12: Femme | H12: Agent commercial | I12: 42775 | J12: 124 | K12: Oui | L12: Duccay keylaneHD | M12: Cutanée et muqueuse | N12: 6 | O12: Autre | P12: Aucun | Q12: Toxidermie | T12: EPF Bulleux
A13: 722452001 | B13: 46123.962 | C13: 46123.972 | D13: 46123 | E13: 780 | F13: 65 | G13: Homme | H13: Cultivateur | I13: 42913 | J13: 93 | K13: Non | M13: Muqueuse seule | N13: 30 | O13: Douleur Fièvre | Q13: Auto-immune | R13: Pemphigoïde bulleuse
A14: 722479386 | B14: 46123.972 | C14: 46124.116 | D14: 46123 | E14: 780 | F14: 65 | G14: Homme | H14: Cultivateur | I14: 42913 | J14: 93 | K14: Non | M14: Cutanée et muqueuse | N14: 20 | O14: Fièvre Autre | P14: Plaies buccales | Q14: Auto-immune | R14: Pemphigoïde bulleuse
A15: 722480056 | B15: 46124.116 | C15: 46124.121 | D15: 46124 | E15: 504 | F15: 42 | G15: Femme | H15: Secrétaire | I15: 42632 | J15: 13 | K15: Oui | L15: Sérum anti tétanique, asmocet L cp | M15: Cutanée et muqueuse | N15: 7 | O15: Autre | P15: Aucun | Q15: Toxidermie | T15: Syndrome de Lyell
A16: 722480377 | B16: 46124.121 | C16: 46124.124 | D16: 46124 | E16: 480 | F16: 40 | G16: Femme | H16: Secrétaire | I16: 42570 | J16: 31 | K16: Non | M16: Cutanée seule | N16: 2 | O16: Autre | P16: Aucun | Q16: Toxidermie | T16: EPF Bulleux
A17: 722480792 | B17: 46124.124 | C17: 46124.127 | D17: 46124 | E17: 564 | F17: 47 | G17: Homme | H17: Technicien | I17: 42535 | J17: 6 | K17: Oui | L17: Forcan 150mg | M17: Cutanée seule | N17: 5 | O17: Autre | P17: Aucun | Q17: Toxidermie | T17: EPF Bulleux
A18: 722482063 | B18: 46124.127 | C18: 46124.134 | D18: 46124 | E18: 288 | F18: 24 | G18: Homme | H18: Pneumatique | I18: 42527 | J18: 4 | K18: Oui | L18: Ceftriaxone inj, gentamicine inj, celestene, Diclofénac, Polaramine | M18: Cutanée seule | N18: 9 | O18: Douleur Prurit | Q18: Toxidermie | T18: Syndrome de chevauchement
A19: 722619425 | B19: 46124.134 | C19: 46124.457 | D19: 46124 | E19: 252 | F19: 21 | G19: Femme | H19: Informaticienne | I19: 42717 | J19: 14 | K19: Oui | L19: Sédaspir cp, ibuprofen cp | M19: Cutanée seule | N19: 33 | O19: Fièvre | Q19: Toxidermie | T19: Syndrome de Stevens Johnson
A20: 722622203 | B20: 46124.457 | C20: 46124.462 | D20: 46124 | E20: 336 | F20: 28 | G20: Homme | H20: Fleuriste | I20: 42621 | J20: 385 | K20: Oui | L20: Griseofulvine, cloxacilline, flagyl cp, | M20: Cutanée et muqueuse | N20: 9 | O20: Autre | P20: Aucun | Q20: Infectieuse | S20: Autre à préciser... | V20: Epidermolyse bulleuse acquise
A21: 722625180 | B21: 46124.462 | C21: 46124.465 | D21: 46124 | E21: 720 | F21: 60 | G21: Femme | H21: Commerçante | I21: 42485 | J21: 3080 | K21: Oui | L21: Cloxacilline | M21: Cutanée seule | N21: 12 | O21: Autre | P21: Aucun | Q21: Toxidermie | T21: EPF Bulleux
A22: 722627814 | B22: 46124.465 | C22: 46124.469 | D22: 46124 | E22: 72 | F22: 6 | G22: Femme | H22: Écolière | I22: 42465 | J22: 7 | K22: Oui | L22: Amoxicilline cp, quinine cp, paracéamol 500mg, bactrim cp, fluconazole suspension, doprex collyre | M22: Cutanée et muqueuse | N22: 80 | O22: Autre | P22: Aucun | Q22: Toxidermie | T22: Syndrome de Stevens Johnson
A23: 722803352 | B23: 46116.637 | C23: 46124.737 | D23: 46116 | E23: 216 | F23: 18 | G23: Homme | H23: Élève | I23: 42830 | J23: 20 | K23: Oui | L23: Ciprofloxacin comprimés | M23: Cutanée seule | N23: 20 | O23: Prurit | Q23: Toxidermie | T23: Autre à préciser... | V23: Érythème polymorphe mineur
A24: 722805963 | B24: 46124.737 | C24: 46124.74 | D24: 46124 | E24: 288 | F24: 24 | G24: Homme | H24: Étudiant | I24: 43229 | J24: 730 | K24: Non | M24: Cutanée seule | N24: 40 | O24: Autre | P24: Aucun | Q24: Auto-immune | R24: Épidermolyse bulleuse acquise
A25: 722807402 | B25: 46124.74 | C25: 46124.742 | D25: 46124 | E25: 144 | F25: 12 | G25: Homme | H25: Écolier | I25: 43108 | J25: 6 | K25: Oui | L25: Phytothérapie | M25: Cutanée et muqueuse | N25: 35 | O25: Douleur | Q25: Toxidermie | T25: Syndrome de chevauchement
A26: 722809657 | B26: 46124.742 | C26: 46124.746 | D26: 46124 | E26: 120 | F26: 10 | G26: Homme | H26: Écolier | I26: 43214 | J26: 8 | K26: Non | M26: Cutanée et muqueuse | N26: 25 | O26: Autre | P26: Frissons | Q26: Toxidermie | T26: Syndrome de chevauchement
A27: 722811313 | B27: 46124.746 | C27: 46124.749 | D27: 46124 | E27: 636 | F27: 53 | G27: Femme | H27: Revendeuse | I27: 43060 | J27: 330 | K27: Non | M27: Cutanée seule | N27: 27 | O27: Prurit | Q27: Auto-immune | R27: Pemphigus paranéoplasique
A28: 722813656 | B28: 46124.749 | C28: 46124.753 | D28: 46124 | E28: 276 | F28: 23 | G28: Homme | H28: Étudiant | I28: 43074 | J28: 3 | K28: Oui | L28: Cotrimoxazole | M28: Cutanée et muqueuse | N28: 5 | O28: Douleur Autre | P28: Sensation de brulure | Q28: Toxidermie | T28: Syndrome de Stevens Johnson
A29: 722815699 | B29: 46124.753 | C29: 46124.757 | D29: 46124 | E29: 84 | F29: 7 | G29: Femme | H29: Écolière | I29: 42934 | J29: 15 | K29: Oui | L29: Amoxicilline, paracétamol cp | M29: Cutanée et muqueuse | N29: 10 | O29: Prurit Fièvre | Q29: Toxidermie | T29: Syndrome de Stevens Johnson
A30: 722818850 | B30: 46124.757 | C30: 46124.762 | D30: 46124 | E30: 36 | F30: 3 | G30: Homme | H30: Aucun | I30: 42901 | J30: 90 | K30: Non | M30: Cutanée seule | N30: 10 | O30: Prurit | Q30: Infectieuse | S30: Épidermolyse staphylococcique
A31: 722820234 | B31: 46124.762 | C31: 46124.765 | D31: 46124 | E31: 36 | F31: 3 | G31: Femme | H31: Aucune | I31: 42919 | J31: 8 | K31: Oui | L31: Coartem, aspirine | M31: Cutanée et muqueuse | N31: 10 | O31: Douleur | Q31: Toxidermie | T31: Syndrome de Stevens Johnson
A32: 722821710 | B32: 46124.765 | C32: 46124.767 | D32: 46124 | E32: 228 | F32: 19 | G32: Femme | H32: Étudiante | I32: 42789 | J32: 21 | K32: Non | M32: Cutanée seule | N32: 25 | O32: Douleur Prurit | Q32: Auto-immune | R32: Dermatite herpétiforme
A33: 722825333 | B33: 46124.767 | C33: 46124.775 | D33: 46124 | E33: 660 | F33: 55 | G33: Femme | H33: Technicienne de laboratoire | I33: 42845 | J33: 5 | K33: Oui | L33: Diclofenac comprimés | M33: Cutanée et muqueuse | N33: 27 | O33: Fièvre | Q33: Toxidermie | T33: Syndrome de chevauchement
A34: 722831716 | B34: 46124.775 | C34: 46124.79 | D34: 46124 | E34: 42 | F34: 3.5 | G34: Homme | H34: Aucune | I34: 42898 | J34: 30 | K34: Non | M34: Cutanée seule | N34: 10 | O34: Prurit | Q34: Infectieuse | S34: Impétigo bulleux
A35: 722832781 | B35: 46124.79 | C35: 46124.793 | D35: 46124 | E35: 372 | F35: 31 | G35: Femme | H35: Commerçante | I35: 42864 | J35: 3 | K35: Oui | L35: Phenobarbital, previscan, myorel, cortancyl | M35: Cutanée et muqueuse | N35: 27 | O35: Fièvre | Q35: Toxidermie | T35: Syndrome de chevauchement
A36: 722835688 | B36: 46124.793 | C36: 46124.798 | D36: 46124 | E36: 708 | F36: 59 | G36: Femme | H36: Retraité | I36: 42947 | J36: 2 | K36: Oui | L36: Xeloda, caprcitabine | M36: Cutanée seule | N36: 2 | O36: Prurit | Q36: Toxidermie | T36: EPF Bulleux
A37: 722837165 | B37: 46124.798 | C37: 46124.801 | D37: 46124 | E37: 216 | F37: 18 | G37: Femme | H37: Élève | I37: 43034 | J37: 7 | K37: Oui | L37: Sulfadoxine-pyriméthamine | M37: Cutanée et muqueuse | N37: 15 | O37: Prurit | Q37: Toxidermie | T37: Syndrome de Stevens Johnson
A38: 722839809 | B38: 46124.801 | C38: 46124.808 | D38: 46124 | E38: 132 | F38: 11 | G38: Homme | H38: Élève | I38: 42905 | J38: 4 | K38: Oui | L38: Sulfadoxine-pyriméthamine, amoxicilline, paracétamol | M38: Muqueuse seule | N38: 3 | O38: Douleur | Q38: Toxidermie | T38: Syndrome de Stevens Johnson
A39: 722904560 | B39: 46124.469 | C39: 46124.972 | D39: 46124 | E39: 636 | F39: 53 | G39: Homme | H39: Agent de PTT | I39: 42410 | J39: 62 | K39: Oui | L39: Erythromicine, flucoxacilline cp, cloxacilline cp | M39: Cutanée et muqueuse | N39: 95 | O39: Autre | P39: Aucun | Q39: Toxidermie | T39: Syndrome de Lyell
A40: 722905279 | B40: 46124.972 | C40: 46124.974 | D40: 46124 | E40: 60 | F40: 5 | G40: Homme | H40: Écolier | I40: 43465 | J40: 3 | K40: Oui | L40: Bactrim cp, paracétamol cp, vermifuge | M40: Cutanée et muqueuse | N40: 95 | O40: Douleur Prurit Fièvre | Q40: Toxidermie | T40: Syndrome de Lyell
A41: 722906161 | B41: 46124.974 | C41: 46124.978 | D41: 46124 | E41: 816 | F41: 68 | G41: Homme | H41: Médecin chirurgien | I41: 43417 | J41: 14 | K41: Oui | L41: Neuroleptil | M41: Cutanée seule | N41: 15 | O41: Prurit | Q41: Toxidermie | T41: EPF Bulleux
A42: 722907257 | B42: 46124.978 | C42: 46124.983 | D42: 46124 | E42: 60 | F42: 5 | G42: Femme | H42: Écolière | I42: 43388 | J42: 1 | K42: Oui | L42: Fucomax cp, Advil sirop, ceftriaxone inj, gentamicine injectable, aspegic injectable | M42: Cutanée seule | N42: 45 | O42: Fièvre | Q42: Toxidermie | T42: Syndrome de Stevens Johnson
A43: 722908296 | B43: 46124.983 | C43: 46124.987 | D43: 46124 | E43: 828 | F43: 69 | G43: Homme | H43: Professeur à la retraite | I43: 43353 | J43: 31 | K43: Oui | L43: Nifelat retard | M43: Cutanée et muqueuse | N43: 20 | O43: Prurit | Q43: Toxidermie | T43: EPF Bulleux
A44: 722909162 | B44: 46124.987 | C44: 46124.991 | D44: 46124 | E44: 216 | F44: 18 | G44: Femme | H44: Apprentie coiffeuse | I44: 43396 | J44: 1 | K44: Oui | L44: Ibuprofene cp, sulfamides cp | M44: Cutanée et muqueuse | N44: 50 | O44: Autre | P44: Aucun | Q44: Toxidermie | T44: Syndrome de Lyell
A45: 722910446 | B45: 46124.991 | C45: 46124.995 | D45: 46124 | E45: 612 | F45: 51 | G45: Femme | H45: Administrateur en gestion de projet | I45: 43384 | J45: 4 | K45: Oui | L45: Métamizole cp, spiramycine cp, metronidazole cp | M45: Cutanée seule | N45: 10 | O45: Prurit Autre | P45: Picotements et chaleur | Q45: Toxidermie | T45: EPF Bulleux
A46: 722913007 | B46: 46124.995 | C46: 46125.003 | D46: 46124 | E46: 396 | F46: 33 | G46: Femme | H46: Commerçante | I46: 43384 | J46: 1925 | K46: Oui | L46: Moringa | M46: Cutanée seule | N46: 20 | O46: Fièvre Autre | P46: Rougeur conjonctivale, érosion buccale | Q46: Toxidermie | T46: EPF Bulleux
A47: 723500929 | B47: 46125.003 | C47: 46125.559 | D47: 46125 | E47: 264 | F47: 22 | G47: Femme | H47: Étudiante | I47: 43319 | J47: 1 | K47: Non | M47: Cutanée seule | N47: 20 | O47: Fièvre | Q47: Toxidermie | T47: Syndrome de Stevens Johnson
A48: 723506643 | B48: 46125.559 | C48: 46125.563 | D48: 46125 | E48: 480 | F48: 40 | G48: Femme | H48: Commerçante | I48: 43433 | J48: 385 | K48: Oui | L48: Nifluril cp, bactrim cp, | M48: Cutanée seule | N48: 6 | O48: Autre | P48: Aucun | Q48: Toxidermie | T48: Syndrome de chevauchement
A49: 723519297 | B49: 46125.563 | C49: 46125.572 | D49: 46125 | E49: 444 | F49: 37 | G49: Homme | H49: Militaire | I49: 43291 | J49: 4 | K49: Oui | L49: Metronidazole cp, powergésic, deslora denk, cotipred, atarax 25mg | M49: Cutanée seule | N49: 30 | O49: Prurit Fièvre | Q49: Toxidermie | T49: EPF Bulleux
A50: 723528166 | B50: 46125.572 | C50: 46125.579 | D50: 46125 | E50: 816 | F50: 68 | G50: Homme | H50: Retraité | I50: 43286 | J50: 385 | K50: Non | M50: Cutanée seule | N50: 2 | O50: Autre | P50: Aucun | Q50: Toxidermie | T50: EPF Bulleux
A51: 726303830 | B51: 46124.808 | C51: 46128.413 | D51: 46124 | E51: 180 | F51: 15 | G51: Homme | H51: Élève | I51: 45747 | J51: 21 | K51: Non | M51: Cutanée et muqueuse | N51: 17 | O51: Douleur Prurit Fièvre | Q51: Infectieuse | S51: Autre à préciser... | V51: Érythème polymorphe majeur
A52: 726306825 | B52: 46128.413 | C52: 46128.415 | D52: 46128 | E52: 192 | F52: 16 | G52: Femme | H52: Élève | I52: 45929 | J52: 3 | K52: Oui | L52: Paracétamol | M52: Cutanée et muqueuse | N52: 20 | O52: Douleur Prurit | Q52: Toxidermie | T52: Autre à préciser... | V52: Érythème polymorphe majeur
A53: 726343086 | B53: 46128.415 | C53: 46128.441 | D53: 46128 | E53: 132 | F53: 11 | G53: Homme | H53: Élève | I53: 45887 | J53: 7 | K53: Oui | L53: Lamotrigine | M53: Cutanée et muqueuse | N53: 12 | O53: Prurit | Q53: Toxidermie | T53: Syndrome de Stevens Johnson
A54: 726483329 | B54: 46128.441 | C54: 46128.542 | D54: 46128 | E54: 900 | F54: 75 | G54: Homme | H54: Enseignant | I54: 45524 | J54: 21 | K54: Non | M54: Cutanée seule | N54: 3 | O54: Douleur Prurit | Q54: Infectieuse | S54: Autre à préciser... | V54: Zona
A55: 726486061 | B55: 46128.542 | C55: 46128.544 | D55: 46128 | E55: 720 | F55: 60 | G55: Femme | H55: Commerçante | I55: 45428 | J55: 60 | K55: Non | M55: Cutanée seule | N55: 6 | O55: Prurit | Q55: Auto-immune | R55: Autre à préciser... | V55: Lupus bulleux
A56: 726493855 | B56: 46128.544 | C56: 46128.55 | D56: 46128 | E56: 396 | F56: 33 | G56: Femme | H56: Comptable | I56: 46042 | J56: 6 | K56: Oui | L56: Non précisé | M56: Cutanée seule | N56: 5 | O56: Prurit | Q56: Toxidermie | T56: EPF Bulleux
A57: 726495267 | B57: 46128.55 | C57: 46128.551 | D57: 46128 | E57: 156 | F57: 13 | G57: Femme | H57: Élève | I57: 46100 | J57: 4 | K57: Non | M57: Cutanée seule | N57: 2 | O57: Douleur | Q57: Infectieuse | S57: Impétigo bulleux
A58: 726513108 | B58: 46128.551 | C58: 46128.564 | D58: 46128 | E58: 36 | F58: 3 | G58: Femme | H58: Aucun | I58: 45859 | J58: 14 | K58: Oui | L58: Amoxicilline, paracétamol cp | M58: Cutanée et muqueuse | N58: 90 | O58: Douleur | Q58: Toxidermie | T58: Syndrome de Lyell
A59: 726515934 | B59: 46128.564 | C59: 46128.566 | D59: 46128 | E59: 144 | F59: 12 | G59: Homme | H59: Élève | I59: 45876 | J59: 7 | K59: Oui | L59: Sulfadoxine-pyriméthamine | M59: Cutanée et muqueuse | N59: 31 | O59: Douleur Prurit | Q59: Toxidermie | T59: Syndrome de Lyell
A60: 726521403 | B60: 46128.566 | C60: 46128.569 | D60: 46128 | E60: 108 | F60: 9 | G60: Homme | H60: Écolier | I60: 45820 | J60: 3 | K60: Oui | L60: Arthemeter lumefantrine, paracétamol | M60: Cutanée et muqueuse | N60: 35 | O60: Douleur | Q60: Toxidermie | T60: Syndrome de Lyell
A61: 726526577 | B61: 46128.569 | C61: 46128.571 | D61: 46128 | E61: 60 | F61: 5 | G61: Homme | H61: Écolier | I61: 45798 | J61: 3 | K61: Non | M61: Cutanée seule | N61: 8 | O61: Prurit | Q61: Infectieuse | S61: Impétigo bulleux
A62: 726532569 | B62: 46128.571 | C62: 46128.574 | D62: 46128 | E62: 648 | F62: 54 | G62: Femme | H62: Ménagère | I62: 43999 | J62: 30 | K62: Non | M62: Cutanée et muqueuse | N62: 45 | O62: Douleur Prurit | Q62: Auto-immune | R62: Pemphigus vulgaire
A63: 726537104 | B63: 46128.574 | C63: 46128.577 | D63: 46128 | E63: 132 | F63: 11 | G63: Homme | H63: Écolier | I63: 44173 | J63: 7 | K63: Non | M63: Cutanée et muqueuse | N63: 8 | O63: Prurit | Q63: Toxidermie | T63: Syndrome de Stevens Johnson
A64: 726539838 | B64: 46128.577 | C64: 46128.578 | D64: 46128 | E64: 60 | F64: 5 | G64: Femme | H64: Écolière | I64: 43915 | J64: 7 | K64: Non | M64: Cutanée seule | N64: 1 | O64: Autre | P64: Aucun | Q64: Infectieuse | S64: Impétigo bulleux
A65: 726543699 | B65: 46128.578 | C65: 46128.58 | D65: 46128 | E65: 900 | F65: 75 | G65: Homme | H65: Guérisseur traditionnel | I65: 44127 | J65: 14 | K65: Oui | L65: Cotrimoxazole | M65: Cutanée et muqueuse | N65: 50 | O65: Douleur Fièvre | Q65: Toxidermie | T65: Syndrome de Lyell
A66: 726548975 | B66: 46128.58 | C66: 46128.583 | D66: 46128 | E66: 60 | F66: 5 | G66: Femme | H66: Écolière | I66: 44167 | J66: 4 | K66: Oui | L66: Cotrimoxazole | M66: Cutanée seule | N66: 15 | O66: Douleur Prurit | Q66: Toxidermie | T66: EPF Bulleux
A67: 726554261 | B67: 46128.583 | C67: 46128.586 | D67: 46128 | E67: 24 | F67: 2 | G67: Homme | H67: Aucun | I67: 44154 | J67: 5 | K67: Oui | L67: Paracétamol, ibuprofène | M67: Cutanée et muqueuse | N67: 31 | O67: Douleur | Q67: Toxidermie | T67: Syndrome de Lyell
A68: 726595677 | B68: 46128.586 | C68: 46128.606 | D68: 46128 | E68: 840 | F68: 70 | G68: Femme | H68: Aucune | I68: 45923 | J68: 6 | K68: Oui | L68: Metamizole sodique | M68: Cutanée seule | N68: 39 | O68: Douleur | Q68: Toxidermie | T68: Syndrome de Lyell
A69: 726600709 | B69: 46128.606 | C69: 46128.608 | D69: 46128 | E69: 876 | F69: 73 | G69: Homme | H69: Aucune | I69: 46058 | J69: 7 | K69: Non | M69: Cutanée seule | N69: 5 | O69: Douleur Prurit | Q69: Auto-immune | R69: Pemphigus vulgaire
A70: 726604770 | B70: 46128.608 | C70: 46128.61 | D70: 46128 | E70: 900 | F70: 75 | G70: Femme | H70: Aucune | I70: 45468 | J70: 30 | K70: Non | M70: Cutanée seule | N70: 1 | O70: Prurit | Q70: Auto-immune | R70: Pemphigoïde bulleuse
A71: 726607612 | B71: 46128.61 | C71: 46128.612 | D71: 46128 | E71: 1164 | F71: 97 | G71: Femme | H71: Aucune | I71: 45356 | J71: 42 | K71: Non | M71: Cutanée seule | N71: 10 | O71: Prurit | Q71: Auto-immune | R71: Pemphigoïde bulleuse
A72: 726613688 | B72: 46128.612 | C72: 46128.615 | D72: 46128 | E72: 91 | F72: 7.6 | G72: Femme | H72: Écolière | I72: 45639 | J72: 15 | K72: Non | M72: Cutanée et muqueuse | N72: 18 | O72: Douleur Prurit | Q72: Toxidermie | T72: Syndrome de chevauchement
A73: 726618268 | B73: 46128.615 | C73: 46128.617 | D73: 46128 | E73: 732 | F73: 61 | G73: Femme | H73: Aucun | I73: 45364 | J73: 10 | K73: Non | M73: Cutanée seule | N73: 17 | O73: Prurit | Q73: Auto-immune | R73: Pemphigoïde bulleuse
A74: 727067760 | B74: 46128.617 | C74: 46128.917 | D74: 46128 | E74: 20 | F74: 1.7 | G74: Homme | H74: Aucune | I74: 44194 | J74: 5 | K74: Oui | L74: Bronquidiazina | M74: Cutanée et muqueuse | N74: 90 | O74: Fièvre | Q74: Toxidermie | T74: Syndrome de Lyell
A75: 727075917 | B75: 46128.917 | C75: 46128.923 | D75: 46128 | E75: 564 | F75: 47 | G75: Femme | H75: Aucune | I75: 44040 | J75: 912 | K75: Non | M75: Cutanée et muqueuse | N75: 20 | O75: Prurit | Q75: Auto-immune | R75: Pemphigus vulgaire
A76: 727075927 | B76: 46128.923 | C76: 46128.926 | D76: 46128 | E76: 60 | F76: 5 | G76: Femme | H76: Écolière | I76: 43748 | J76: 730 | K76: Non | M76: Cutanée et muqueuse | N76: 6 | O76: Prurit | Q76: Toxidermie | T76: EPF Bulleux
A77: 727075931 | B77: 46128.926 | C77: 46128.929 | D77: 46128 | E77: 672 | F77: 56 | G77: Femme | H77: Commerçante | I77: 43871 | J77: 21 | K77: Non | M77: Cutanée et muqueuse | N77: 40 | O77: Douleur Prurit | Q77: Auto-immune | R77: Pemphigus paranéoplasique
A78: 727075934 | B78: 46128.929 | C78: 46128.931 | D78: 46128 | E78: 624 | F78: 52 | G78: Homme | H78: Comptable | I78: 45265 | J78: 7 | K78: Non | M78: Cutanée et muqueuse | N78: 30 | O78: Prurit | Q78: Auto-immune | R78: Pemphigoïde bulleuse
A79: 727075938 | B79: 46128.931 | C79: 46128.933 | D79: 46128 | E79: 852 | F79: 71 | G79: Femme | H79: Couturière | I79: 43745 | J79: 7 | K79: Non | M79: Cutanée et muqueuse | N79: 7 | O79: Douleur Prurit | Q79: Auto-immune | R79: Pemphigoïde bulleuse
A80: 727169159 | B80: 46128.933 | C80: 46129.159 | D80: 46128 | E80: 552 | F80: 46 | G80: Femme | H80: Non précisé | I80: 45233 | J80: 5 | K80: Non | M80: Cutanée seule | N80: 14 | O80: Douleur | Q80: Infectieuse | S80: Impétigo bulleux
A81: 727169164 | B81: 46129.159 | C81: 46129.162 | D81: 46129 | E81: 48 | F81: 4 | G81: Homme | H81: Écolier | I81: 45237 | J81: 1458 | K81: Non | M81: Cutanée et muqueuse | N81: 15 | O81: Prurit | Q81: Auto-immune | R81: Autre à préciser... | V81: Epidermolyse bulleuse héréditaire
A82: 727169171 | B82: 46129.162 | C82: 46129.166 | D82: 46129 | E82: 552 | F82: 46 | G82: Femme | H82: Infirmière | I82: 45412 | J82: 657 | K82: Non | M82: Cutanée seule | N82: 4 | O82: Prurit | Q82: Immunoallergique | U82: Autre à préciser... | V82: Lichen bulleux
A83: 727169173 | B83: 46129.166 | C83: 46129.167 | D83: 46129 | E83: 11 | F83: 0.9 | G83: Femme | H83: Aucune | I83: 45469 | J83: 4 | K83: Non | M83: Cutanée seule | N83: 10 | O83: Prurit | Q83: Infectieuse | S83: Impétigo bulleux
A84: 727169177 | B84: 46129.167 | C84: 46129.169 | D84: 46129 | E84: 552 | F84: 46 | G84: Homme | H84: Juriste | I84: 45435 | J84: 30 | K84: Non | M84: Cutanée seule | N84: 10 | O84: Douleur | Q84: Infectieuse | S84: DHBANN
A85: 727254557 | B85: 46129.169 | C85: 46129.28 | D85: 46129 | E85: 564 | F85: 47 | G85: Homme | H85: Commerçant | I85: 45546 | J85: 7 | K85: Oui | L85: Paracétamol, phytothérapie | M85: Cutanée et muqueuse | N85: 22 | O85: Douleur Prurit | Q85: Toxidermie | T85: EPF Bulleux
A86: 727363670 | B86: 46129.28 | C86: 46129.369 | D86: 46129 | E86: 624 | F86: 52 | G86: Femme | H86: Commerçante | I86: 45489 | J86: 730 | K86: Non | M86: Cutanée seule | N86: 15 | O86: Douleur | Q86: Immunoallergique | U86: Autre à préciser... | V86: Lichen bulleux
A87: 727368762 | B87: 46129.369 | C87: 46129.373 | D87: 46129 | E87: 972 | F87: 81 | G87: Homme | H87: Chauffeur | I87: 45523 | J87: 14 | K87: Oui | L87: Non précisé | M87: Muqueuse seule | N87: 3 | O87: Prurit | Q87: Toxidermie | T87: EPF Bulleux
A88: 727375146 | B88: 46129.373 | C88: 46129.377 | D88: 46129 | E88: 792 | F88: 66 | G88: Femme | H88: Commerçante | I88: 45534 | J88: 365 | K88: Non | M88: Cutanée seule | N88: 15 | O88: Prurit | Q88: Auto-immune | R88: Pemphigus paranéoplasique
A89: 727381382 | B89: 46129.377 | C89: 46129.381 | D89: 46129 | E89: 840 | F89: 70 | G89: Femme | H89: Commerçante | I89: 46038 | J89: 6 | K89: Oui | L89: Cotrimoxazole | M89: Cutanée seule | N89: 47 | O89: Douleur | Q89: Toxidermie | T89: Syndrome de Lyell
A90: 727387342 | B90: 46129.381 | C90: 46129.385 | D90: 46129 | E90: 18 | F90: 1.5 | G90: Homme | H90: Aucun | I90: 45406 | J90: 2 | K90: Non | M90: Cutanée seule | N90: 1 | O90: Prurit | Q90: Infectieuse | S90: Impétigo bulleux
A91: 727394807 | B91: 46129.385 | C91: 46129.39 | D91: 46129 | E91: 552 | F91: 46 | G91: Homme | H91: Directeur de microfinances | I91: 46043 | J91: 4 | K91: Oui | L91: Arthemeter lumefantrine | M91: Cutanée et muqueuse | N91: 5 | O91: Douleur | Q91: Toxidermie | T91: Syndrome de Stevens Johnson
A92: 727401585 | B92: 46129.39 | C92: 46129.395 | D92: 46129 | E92: 1164 | F92: 97 | G92: Femme | H92: Aucune | I92: 46106 | J92: 60 | K92: Non | M92: Cutanée seule | N92: 15 | O92: Douleur | Q92: Auto-immune | R92: Pemphigoïde bulleuse
A93: 727409977 | B93: 46129.395 | C93: 46129.402 | D93: 46129 | E93: 912 | F93: 76 | G93: Femme | H93: Commerçante | I93: 46111 | J93: 60 | K93: Non | M93: Cutanée seule | N93: 14 | O93: Douleur | Q93: Auto-immune | R93: Autre à préciser... | V93: Lupus bulleux
A94: 727417895 | B94: 46129.402 | C94: 46129.407 | D94: 46129 | E94: 792 | F94: 66 | G94: Femme | H94: Aucune | I94: 45362 | J94: 210 | K94: Non | M94: Cutanée seule | N94: 6 | O94: Prurit | Q94: Auto-immune | R94: Pemphigoïde bulleuse
A95: 727422558 | B95: 46129.407 | C95: 46129.41 | D95: 46129 | E95: 948 | F95: 79 | G95: Homme | H95: Réalisateur de films | I95: 46049 | J95: 35 | K95: Non | M95: Cutanée seule | N95: 10 | O95: Prurit | Q95: Auto-immune | R95: Pemphigus vulgaire
A96: 727427192 | B96: 46129.41 | C96: 46129.414 | D96: 46129 | E96: 648 | F96: 54 | G96: Femme | H96: Commerçante | I96: 45406 | J96: 90 | K96: Non | M96: Cutanée seule | N96: 12 | O96: Prurit | Q96: Immunoallergique | U96: Autre à préciser... | V96: Lichen bulleux
A97: 727560327 | B97: 46129.414 | C97: 46129.523 | D97: 46129 | E97: 528 | F97: 44 | G97: Homme | H97: Mécanicien | I97: 44179 | J97: 14 | K97: Oui | L97: Paracétamol | M97: Cutanée et muqueuse | N97: 26 | O97: Douleur Prurit | Q97: Toxidermie | T97: Syndrome de Stevens Johnson
A98: 727564575 | B98: 46129.523 | C98: 46129.526 | D98: 46129 | E98: 72 | F98: 6 | G98: Homme | H98: Écolier | I98: 43955 | J98: 3 | K98: Oui | L98: Sulfadoxine-pyriméthamine | M98: Cutanée et muqueuse | N98: 9 | O98: Douleur | Q98: Toxidermie | T98: Syndrome de Stevens Johnson
A99: 727575819 | B99: 46129.526 | C99: 46129.535 | D99: 46129 | E99: 72 | F99: 6 | G99: Femme | H99: Écolière | I99: 43676 | J99: 12 | K99: Non | M99: Cutanée seule | N99: 7 | O99: Prurit | Q99: Infectieuse | S99: Épidermolyse staphylococcique
A100: 727580014 | B100: 46129.535 | C100: 46129.538 | D100: 46129 | E100: 36 | F100: 3 | G100: Homme | H100: Aucune | I100: 43544 | J100: 180 | K100: Non | M100: Cutanée seule | N100: 6 | O100: Prurit | Q100: Infectieuse | S100: Impétigo bulleux
...

Sheet Rapport_Etude
A1: RAPPORT D'ÉTUDE : DERMATOSES BULLEUSES AU CNHU HKM
A2: Structure IMRAD (Introduction, Méthodes, Résultats, And Discussion)
A4: 1. INTRODUCTION
A6: 1.1 Contexte et Justification
A7: Les dermatoses bulleuses constituent un groupe hétérogène d'affections cutanées caractérisées par la formation de bulles. Ces pathologies, bien que relativement rares, présentent un intérêt clinique majeur en raison de leur potentiel de gravité et de leur impact sur la qualité de vie des patients. Au Centre National Hospitalier Universitaire Hubert Koutoukou Maga (CNHU HKM) du Bénin, ces affections représentent une part significative des consultations dermatologiques.
A9: Cette étude vise à analyser le profil épidémiologique, clinique et étiologique des dermatoses bulleuses observées au CNHU HKM, afin d'identifier les facteurs de risque et les patterns cliniques caractéristiques de chaque catégorie diagnostique.
A11: 1.2 Objectifs de l'étude
A12: • Décrire les caractéristiques démographiques et cliniques des patients atteints de dermatoses bulleuses
A13: • Identifier les facteurs associés à chaque catégorie de dermatose (Toxidermie, Auto-immune, Infectieuse, Immunoallergique)
A14: • Évaluer les facteurs prédictifs de sévérité, notamment pour les toxidermies graves (Syndrome de Stevens-Johnson et Lyell)
A15: • Proposer une classification des patients par analyse de clustering
A16: • Formuler des recommandations pour la prise en charge clinique
... A21: 2.1 Type et cadre de l'étude
A22: Type d'étude: | B22: Étude transversale descriptive et analytique
A23: Lieu: | B23: Service de Dermatologie, CNHU HKM, Cotonou, Bénin
A24: Période: | B24: 2016-2019 (consultations de Janvier 2016 à Décembre 2018)
A25: Population: | B25: Patients présentant une dermatose bulleuse confirmée cliniquement
A27: 2.2 Population d'étude
A28: Effectif total analysé: | B28: =Rapport_Complet!B6 -> 130
A30: Critères d'inclusion:
A31: • Patients de tout âge consultant pour une dermatose bulleuse
A32: • Diagnostic clinique confirmé par un dermatologue
A33: • Dossier médical complet avec les variables d'intérêt
A35: 2.3 Variables étudiées (22 variables sources)
A36: Catégorie | B36: Variables | C36: Description
A37: Démographiques | B37: Âge, Sexe, Profession | C37: Caractéristiques socio-démographiques
A38: Temporelles | B38: Date consultation, Délai consultation | C38: Aspects chronologiques
A39: Médicamenteuses | B39: Prise médicamenteuse, Médicament(s) | C39: Exposition aux médicaments
A40: Cliniques | B40: Type d'atteinte, Surface corporelle, Signes associés | C40: Manifestations cliniques
A41: Diagnostiques | B41: Catégorie dermatose, Sous-types spécifiques | C41: Classification nosologique
A42: Dérivées | B42: Sévérité, Classes médicamenteuses, Groupe d'âge | C42: Variables calculées pour l'analyse
A44: 2.4 Analyses statistiques
A45: Méthode | B45: Application | C45: Logiciel
A46: Statistiques descriptives | B46: Moyennes, médianes, écart-types, IC 95% | C46: Excel + Python
A47: Test Chi² d'indépendance | B47: Association entre variables catégorielles | C47: Excel
A48: Régression logistique multivariée | B48: Facteurs prédictifs par catégorie de dermatose | C48: Python (statsmodels)
A49: Clustering K-Means | B49: Classification non supervisée (K=4 clusters) | C49: Python (scikit-learn)
A50: Clustering Hiérarchique | B50: Méthode de Ward avec distance de Gower | C50: Python (scipy)
A51: Indices de validation | B51: Silhouette, Calinski-Harabasz, Davies-Bouldin | C51: Python
A52: Seuil de significativité | B52: p < 0.05 | C52: -
A55: 3. RÉSULTATS
A57: 3.1 Caractéristiques de la population étudiée
A59: Paramètre | B59: Valeur | C59: Source | D59: Source
A60: Effectif total | B60: =Rapport_Complet!B6 -> 130 | C60: Rapport_Complet
A61: Âge moyen (années) | B61: =Rapport_Complet!B10 -> 36.086923 | C61: Rapport_Complet
A62: Âge médian (années) | B62: =Rapport_Complet!B11 -> 33 | C62: Rapport_Complet
A63: Écart-type âge | B63: =Rapport_Complet!B13 -> 25.733801 | C63: Rapport_Complet
A64: Sexe féminin (n) | B64: =Rapport_Complet!B17 -> 74 | C64: Rapport_Complet
A65: Sexe féminin (%) | B65: =Rapport_Complet!C17 -> 56.923077 | C65: Rapport_Complet
A66: Surface corporelle moyenne (%) | B66: =Rapport_Complet!B33 -> 24.853846 | C66: Rapport_Complet
A67: Surface corporelle médiane (%) | B67: =Rapport_Complet!B34 -> 15 | C67: Rapport_Complet
A68: Prise médicamenteuse Oui (n) | B68: =Rapport_Complet!B22 -> 68 | C68: Rapport_Complet
A71: 3.2 Répartition par tranche d'âge
A73: Tranche d'âge | B73: Effectif | C73: Pourcentage
A74: 0-18 ans (Pédiatrique) | B74: =Rapport_Complet!B89 -> 43 | C74: =Rapport_Complet!C89 -> 33.076923
A75: 19-59 ans (Adulte) | B75: =Rapport_Complet!B90 -> 58 | C75: =Rapport_Complet!C90 -> 44.615385
A76: 60 ans et plus (Gériatrique) | B76: =Rapport_Complet!B91 -> 29 | C76: =Rapport_Complet!C91 -> 22.307692
A77: TOTAL | B77: =Rapport_Complet!B92 -> 130 | C77: 100
A80: 3.3 Distribution des catégories de dermatose
A82: Catégorie | B82: Effectif | C82: Pourcentage | D82: Chi²
A83: Toxidermie | B83: =Rapport_Complet!B47 -> 75 | C83: =Rapport_Complet!C47 -> 57.692308 | D83: =Analyse_Statistique!F15 -> 55.576923
A84: Auto-immune | B84: =Rapport_Complet!B48 -> 31 | C84: =Rapport_Complet!C48 -> 23.846154 | D84: =Analyse_Statistique!F16 -> 0.069230769
A85: Infectieuse | B85: =Rapport_Complet!B49 -> 19 | C85: =Rapport_Complet!C49 -> 14.615385 | D85: =Analyse_Statistique!F17 -> 5.6076923
A86: Immunoallergique | B86: =Rapport_Complet!B50 -> 5 | C86: =Rapport_Complet!C50 -> 3.8461538 | D86: =Analyse_Statistique!F18 -> 23.269231
A87: TOTAL | B87: =SUM(B83:B86) -> 130 | C87: 100 | D87: =Analyse_Statistique!F19 -> 84.523077
A89: Interprétation: p-value < 0.0001 → La distribution est significativement non uniforme, avec une nette prédominance des toxidermies.
A92: 3.4 Sous-types de Toxidermie
A94: Sous-type | B94: Effectif | C94: Pourcentage
A95: EPF Bulleux | B95: =Rapport_Complet!B71 -> 25 | C95: =Rapport_Complet!C71 -> 19.230769
A96: Syndrome de Stevens-Johnson | B96: =Rapport_Complet!B72 -> 20 | C96: =Rapport_Complet!C72 -> 15.384615
A97: Syndrome de Lyell | B97: =Rapport_Complet!B73 -> 15 | C97: =Rapport_Complet!C73 -> 11.538462
A98: Syndrome de chevauchement | B98: =Rapport_Complet!B74 -> 8 | C98: =Rapport_Complet!C74 -> 6.1538462
A99: Autre | B99: =Rapport_Complet!B75 -> 7 | C99: =Rapport_Complet!C75 -> 5.3846154
A101: Toxidermies sévères (SJS + Lyell): | B101: =Statistic_Analysis!B35 -> 35 | C101: cas soit | D101: =Statistic_Analysis!C35 -> 0.2692
A104: 3.5 Analyse multivariée - Modèle Toxidermie
A106: Variable | B106: Coefficient (β) | C106: Erreur Std | D106: Wald z | E106: p-value | F106: Odds Ratio | G106: IC 95% Inf | H106: IC 95% Sup
A107: Intercept (β₀) | B107: =Statistic_Analysis!B47 -> 0.31 | C107: =Statistic_Analysis!C47 -> 0.45 | D107: =Statistic_Analysis!D47 -> 0.6892 | E107: =Statistic_Analysis!E47 -> 0.4907 | F107: =Statistic_Analysis!F47 -> 1.3636 | G107: =Statistic_Analysis!G47 -> 0.5645 | H107: =Statistic_Analysis!H47 -> 3.2942
A108: Âge (années) | B108: =Statistic_Analysis!B48 -> -0.025 | C108: =Statistic_Analysis!C48 -> 0.008 | D108: =Statistic_Analysis!D48 -> -3.125 | E108: =Statistic_Analysis!E48 -> 0.0018 | F108: =Statistic_Analysis!F48 -> 0.9753 | G108: =Statistic_Analysis!G48 -> 0.9601 | H108: =Statistic_Analysis!H48 -> 0.9907
A109: Sexe (Femme=1) | B109: =Statistic_Analysis!B49 -> 0.04 | C109: =Statistic_Analysis!C49 -> 0.38 | D109: =Statistic_Analysis!D49 -> 0.104 | E109: =Statistic_Analysis!E49 -> 0.9171 | F109: =Statistic_Analysis!F49 -> 1.0403 | G109: =Statistic_Analysis!G49 -> 0.494 | H109: =Statistic_Analysis!H49 -> 2.1909
A110: Prise médicamenteuse | B110: =Statistic_Analysis!B50 -> 4.724 | C110: =Statistic_Analysis!C50 -> 0.52 | D110: =Statistic_Analysis!D50 -> 9.0854 | E110: =Statistic_Analysis!E50 -> <0.0001 | F110: =Statistic_Analysis!F50 -> 112.6667 | G110: =Statistic_Analysis!G50 -> 40.6595 | H110: =Statistic_Analysis!H50 -> 312.1968
A111: Type atteinte (Mixte) | B111: =Statistic_Analysis!B51 -> 0.185 | C111: =Statistic_Analysis!C51 -> 0.41 | D111: =Statistic_Analysis!D51 -> 0.4512 | E111: =Statistic_Analysis!E51 -> 0.6518 | F111: =Statistic_Analysis!F51 -> 1.2033 | G111: =Statistic_Analysis!G51 -> 0.5385 | H111: =Statistic_Analysis!H51 -> 2.6878
A112: Surface corporelle (%) | B112: =Statistic_Analysis!B52 -> 0.012 | C112: =Statistic_Analysis!C52 -> 0.005 | D112: =Statistic_Analysis!D52 -> 2.4 | E112: =Statistic_Analysis!E52 -> 0.0164 | F112: =Statistic_Analysis!F52 -> 1.0121 | G112: =Statistic_Analysis!G52 -> 1.0022 | H112: =Statistic_Analysis!H52 -> 1.022
A114: Performance du modèle Toxidermie:
A115: Pseudo R² (McFadden) | B115: =Statistic_Analysis!B56 -> 0.4215
A116: AUC-ROC | B116: =Statistic_Analysis!B57 -> 0.942
A117: Accuracy | B117: =Statistic_Analysis!B58 -> 0.9
A118: Sensibilité | B118: =Statistic_Analysis!B59 -> 0.8667
A119: Spécificité | B119: =Statistic_Analysis!B60 -> 0.9455
A122: 3.6 Synthèse des modèles de régression logistique
A124: Modèle | B124: Pseudo R² | C124: AUC-ROC | D124: Accuracy | E124: Sensibilité | F124: Spécificité
A125: Toxidermie | B125: =Statistic_Analysis!B56 -> 0.4215 | C125: =Statistic_Analysis!B57 -> 0.942 | D125: =Statistic_Analysis!B58 -> 0.9 | E125: =Statistic_Analysis!B59 -> 0.8667 | F125: =Statistic_Analysis!B60 -> 0.9455
A126: Auto-immune | B126: =Statistic_Analysis!B79 -> 0.2075 | C126: =Statistic_Analysis!B80 -> 0.8245 | D126: =Statistic_Analysis!B81 -> 0.8231 | E126: =Statistic_Analysis!B82 -> 0.6452 | F126: =Statistic_Analysis!B83 -> 0.8788
A127: Infectieuse | B127: =Statistic_Analysis!B102 -> 0.3999 | C127: =Statistic_Analysis!B103 -> 0.8756 | D127: =Statistic_Analysis!B104 -> 0.8923 | E127: =Statistic_Analysis!B105 -> 0.5263 | F127: =Statistic_Analysis!B106 -> 0.955
A128: Immunoallergique* | B128: =Statistic_Analysis!B126 -> 0.1248 | C128: =Statistic_Analysis!B127 -> 0.685 | D128: =Statistic_Analysis!B128 -> 0.9615 | E128: 0 | F128: -
A130: * Effectif faible (n=5) - Résultats à interpréter avec prudence
A133: 3.7 Facteurs prédictifs significatifs (p < 0.05)
A135: Catégorie | B135: Facteur | C135: Odds Ratio | D135: Interprétation
A136: TOXIDERMIE | B136: Prise médicamenteuse | C136: =Statistic_Analysis!F50 -> 112.6667 | D136: Facteur de risque majeur (OR ≈ 113)
A137: TOXIDERMIE | B137: Âge (jeune) | C137: =Statistic_Analysis!F48 -> 0.9753 | D137: Protection relative (OR < 1)
A138: TOXIDERMIE | B138: Surface corporelle | C138: =Statistic_Analysis!F52 -> 1.0121 | D138: Association positive (OR ≈ 1.01)
...

Sheet Rapport_Complet
A1: RAPPORT DERMATOSES BULLEUSES CNHU HKM
A4: SECTION 1: POPULATION TOTALE
A6: Nombre total de répondants: | B6: =COUNTA('Dermatoses Bulleuses CNHU HKM'!A:A)-1 -> 130
A8: STATISTIQUES D'ÂGE (en années)
A9: Statistique | B9: Valeur
A10: Moyenne | B10: =AVERAGE('Dermatoses Bulleuses CNHU HKM'!F2:F131) -> 36.086923
A11: Médiane | B11: =MEDIAN('Dermatoses Bulleuses CNHU HKM'!F2:F131) -> 33
A12: Mode | B12: =_xlfn.MODE.SNGL('Dermatoses Bulleuses CNHU HKM'!F2:F131) -> 46
A13: Écart-type | B13: =_xlfn.STDEV.P('Dermatoses Bulleuses CNHU HKM'!F2:F131) -> 25.733801
A15: SEXE
A16: Valeur | B16: Fréquence | C16: Pourcentage
A17: Femme | B17: =COUNTIF('Dermatoses Bulleuses CNHU HKM'!G:G,"Femme") -> 74 | C17: =B17/$B$6*100 -> 56.923077
A18: Homme | B18: =COUNTIF('Dermatoses Bulleuses CNHU HKM'!G:G,"Homme") -> 56 | C18: =B18/$B$6*100 -> 43.076923
A20: NOTION DE PRISE MÉDICAMENTEUSE
A21: Valeur | B21: Fréquence | C21: Pourcentage
A22: Oui | B22: =COUNTIF('Dermatoses Bulleuses CNHU HKM'!K:K,"Oui") -> 68 | C22: =B22/$B$6*100 -> 52.307692
A23: Non | B23: =COUNTIF('Dermatoses Bulleuses CNHU HKM'!K:K,"Non") -> 62 | C23: =B23/$B$6*100 -> 47.692308
A25: TYPE D'ATTEINTE
A26: Valeur | B26: Fréquence | C26: Pourcentage
A27: Cutanée seule | B27: =COUNTIF('Dermatoses Bulleuses CNHU HKM'!M:M,"Cutanée seule") -> 67 | C27: =B27/$B$6*100 -> 51.538462
A28: Cutanée et muqueuse | B28: =COUNTIF('Dermatoses Bulleuses CNHU HKM'!M:M,"Cutanée et muqueuse") -> 60 | C28: =B28/$B$6*100 -> 46.153846
A29: Muqueuse seule | B29: =COUNTIF('Dermatoses Bulleuses CNHU HKM'!M:M,"Muqueuse seule") -> 3 | C29: =B29/$B$6*100 -> 2.3076923
A31: SURFACE CORPORELLE ATTEINTE
A32: Statistique | B32: Valeur
A33: Moyenne | B33: =AVERAGE('Dermatoses Bulleuses CNHU HKM'!N2:N131) -> 24.853846
A34: Médiane | B34: =MEDIAN('Dermatoses Bulleuses CNHU HKM'!N2:N131) -> 15
A35: Mode | B35: =_xlfn.MODE.SNGL('Dermatoses Bulleuses CNHU HKM'!N2:N131) -> 10
A36: Écart-type | B36: =_xlfn.STDEV.P('Dermatoses Bulleuses CNHU HKM'!N2:N131) -> 24.846022
A38: SIGNES ASSOCIÉS
A39: Valeur | B39: Fréquence | C39: Pourcentage
A40: Prurit | B40: {=SUMPRODUCT(--(ISNUMBER(SEARCH("Prurit",'Dermatoses Bulleuses CNHU HKM'!O2:O131))))} -> 71 | C40: =B40/$B$6*100 -> 54.615385
A41: Douleur | B41: {=SUMPRODUCT(--(ISNUMBER(SEARCH("Douleur",'Dermatoses Bulleuses CNHU HKM'!O2:O131))))} -> 55 | C41: =B41/$B$6*100 -> 42.307692
A42: Fièvre | B42: {=SUMPRODUCT(--(ISNUMBER(SEARCH("Fièvre",'Dermatoses Bulleuses CNHU HKM'!O2:O131))))} -> 18 | C42: =B42/$B$6*100 -> 13.846154
A43: Autre | B43: {=SUMPRODUCT(--(ISNUMBER(SEARCH("Autre",'Dermatoses Bulleuses CNHU HKM'!O2:O131))))} -> 25 | C43: =B43/$B$6*100 -> 19.230769
A45: CATÉGORIE DE LA DERMATOSE
A46: Valeur | B46: Fréquence | C46: Pourcentage
A47: Toxidermie | B47: =COUNTIF('Dermatoses Bulleuses CNHU HKM'!Q:Q,"Toxidermie") -> 75 | C47: =B47/$B$6*100 -> 57.692308
A48: Auto-immune | B48: =COUNTIF('Dermatoses Bulleuses CNHU HKM'!Q:Q,"Auto-immune") -> 31 | C48: =B48/$B$6*100 -> 23.846154
A49: Infectieuse | B49: =COUNTIF('Dermatoses Bulleuses CNHU HKM'!Q:Q,"Infectieuse") -> 19 | C49: =B49/$B$6*100 -> 14.615385
A50: Immunoallergique | B50: =COUNTIF('Dermatoses Bulleuses CNHU HKM'!Q:Q,"Immunoallergique") -> 5 | C50: =B50/$B$6*100 -> 3.8461538
A52: DERMATOSE AUTO-IMMUNE
A53: Valeur | B53: Fréquence | C53: Pourcentage
A54: Pemphigoïde bulleuse | B54: =COUNTIF('Dermatoses Bulleuses CNHU HKM'!R:R,"Pemphigoïde bulleuse") -> 15 | C54: =B54/$B$6*100 -> 11.538462
A55: Pemphigus vulgaire | B55: =COUNTIF('Dermatoses Bulleuses CNHU HKM'!R:R,"Pemphigus vulgaire") -> 7 | C55: =B55/$B$6*100 -> 5.3846154
A56: Pemphigus paranéoplasique | B56: =COUNTIF('Dermatoses Bulleuses CNHU HKM'!R:R,"Pemphigus paranéoplasique") -> 3 | C56: =B56/$B$6*100 -> 2.3076923
A57: Dermatose à IgA linéaire | B57: =COUNTIF('Dermatoses Bulleuses CNHU HKM'!R:R,"Dermatose à IgA linéaire") -> 1 | C57: =B57/$B$6*100 -> 0.76923077
A58: Épidermolyse bulleuse acquise | B58: =COUNTIF('Dermatoses Bulleuses CNHU HKM'!R:R,"Épidermolyse bulleuse acquise") -> 1 | C58: =B58/$B$6*100 -> 0.76923077
A59: Dermatite herpétiforme | B59: =COUNTIF('Dermatoses Bulleuses CNHU HKM'!R:R,"Dermatite herpétiforme") -> 1 | C59: =B59/$B$6*100 -> 0.76923077
A60: Autre à préciser... | B60: =COUNTIF('Dermatoses Bulleuses CNHU HKM'!R:R,"Autre à préciser...") -> 3 | C60: =B60/$B$6*100 -> 2.3076923
A62: DERMATOSE INFECTIEUSE
A63: Valeur | B63: Fréquence | C63: Pourcentage
A64: Impétigo bulleux | B64: =COUNTIF('Dermatoses Bulleuses CNHU HKM'!S:S,"Impétigo bulleux") -> 10 | C64: =B64/$B$6*100 -> 7.6923077
A65: Épidermolyse staphylococcique | B65: =COUNTIF('Dermatoses Bulleuses CNHU HKM'!S:S,"Épidermolyse staphylococcique") -> 3 | C65: =B65/$B$6*100 -> 2.3076923
A66: DHBANN | B66: =COUNTIF('Dermatoses Bulleuses CNHU HKM'!S:S,"DHBANN") -> 2 | C66: =B66/$B$6*100 -> 1.5384615
A67: Autre à préciser... | B67: =COUNTIF('Dermatoses Bulleuses CNHU HKM'!S:S,"Autre à préciser...") -> 4 | C67: =B67/$B$6*100 -> 3.0769231
A69: TOXIDERMIE
A70: Valeur | B70: Fréquence | C70: Pourcentage
A71: EPF Bulleux | B71: =COUNTIF('Dermatoses Bulleuses CNHU HKM'!T:T,"EPF Bulleux") -> 25 | C71: =B71/$B$6*100 -> 19.230769
A72: Syndrome de Stevens Johnson | B72: =COUNTIF('Dermatoses Bulleuses CNHU HKM'!T:T,"Syndrome de Stevens Johnson") -> 20 | C72: =B72/$B$6*100 -> 15.384615
A73: Syndrome de Lyell | B73: =COUNTIF('Dermatoses Bulleuses CNHU HKM'!T:T,"Syndrome de Lyell") -> 15 | C73: =B73/$B$6*100 -> 11.538462
A74: Syndrome de chevauchement | B74: =COUNTIF('Dermatoses Bulleuses CNHU HKM'!T:T,"Syndrome de chevauchement") -> 8 | C74: =B74/$B$6*100 -> 6.1538462
A75: Autre à préciser... | B75: =COUNTIF('Dermatoses Bulleuses CNHU HKM'!T:T,"Autre à préciser...") -> 7 | C75: =B75/$B$6*100 -> 5.3846154
A77: DÉLAI DE CONSULTATION (en jours)
A78: Statistique | B78: Valeur
A79: Moyenne | B79: =AVERAGE('Dermatoses Bulleuses CNHU HKM'!J2:J131) -> 141.33846
A80: Médiane | B80: =MEDIAN('Dermatoses Bulleuses CNHU HKM'!J2:J131) -> 14
A81: Mode | B81: =_xlfn.MODE.SNGL('Dermatoses Bulleuses CNHU HKM'!J2:J131) -> 7
A82: Écart-type | B82: =_xlfn.STDEV.P('Dermatoses Bulleuses CNHU HKM'!J2:J131) -> 414.81623
A85: SECTION 2: ANALYSE PAR TRANCHE D'ÂGE
A87: RÉPARTITION PAR TRANCHE D'ÂGE
A88: Tranche d'âge | B88: Fréquence | C88: Pourcentage
A89: 0-18 ans | B89: =COUNTIFS(Dermatoses_Bulleuses_CNHU_HKM[age_years_calc],">=0",Dermatoses_Bulleuses_CNHU_HKM[age_years_calc],"<=18") -> 43 | C89: =B89/$B$6*100 -> 33.076923
A90: 19-59 ans | B90: =COUNTIFS(Dermatoses_Bulleuses_CNHU_HKM[age_years_calc],">=19",Dermatoses_Bulleuses_CNHU_HKM[age_years_calc],"<=59") -> 58 | C90: =B90/$B$6*100 -> 44.615385
A91: 60 ans et plus | B91: =COUNTIF(Dermatoses_Bulleuses_CNHU_HKM[age_years_calc],">=60") -> 29 | C91: =B91/$B$6*100 -> 22.307692
A92: TOTAL | B92: =SUM(B89:B91) -> 130 | C92: =SUM(C89:C91) -> 100
A95: 2.1 TRANCHE D'ÂGE: 0-18 ANS
A97: Effectif (0-18 ans): | B97: =B89 -> 43
A99: SEXE (0-18 ans)
A100: Valeur | B100: Fréquence | C100: Pourcentage
A101: Femme | B101: =COUNTIFS(Dermatoses_Bulleuses_CNHU_HKM[age_years_calc],">=0",Dermatoses_Bulleuses_CNHU_HKM[age_years_calc],"<=18",Dermatoses_Bulleuses_CNHU_HKM[Sexe],"Femme") -> 19 | C101: =B101/$B$97*100 -> 44.186047
A102: Homme | B102: =COUNTIFS(Dermatoses_Bulleuses_CNHU_HKM[age_years_calc],">=0",Dermatoses_Bulleuses_CNHU_HKM[age_years_calc],"<=18",Dermatoses_Bulleuses_CNHU_HKM[Sexe],"Homme") -> 24 | C102: =B102/$B$97*100 -> 55.813953
A104: NOTION DE PRISE MÉDICAMENTEUSE (0-18 ans)
A105: Valeur | B105: Fréquence | C105: Pourcentage
A106: Oui | B106: =COUNTIFS(Dermatoses_Bulleuses_CNHU_HKM[age_years_calc],">=0",Dermatoses_Bulleuses_CNHU_HKM[age_years_calc],"<=18",Dermatoses_Bulleuses_CNHU_HKM[Notion de prise médicamenteuse],"Oui") -> 23 | C106: =B106/$B$97*100 -> 53.488372
A107: Non | B107: =COUNTIFS(Dermatoses_Bulleuses_CNHU_HKM[age_years_calc],">=0",Dermatoses_Bulleuses_CNHU_HKM[age_years_calc],"<=18",Dermatoses_Bulleuses_CNHU_HKM[Notion de prise médicamenteuse],"Non") -> 20 | C107: =B107/$B$97*100 -> 46.511628
A109: TYPE D'ATTEINTE (0-18 ans)
A110: Valeur | B110: Fréquence | C110: Pourcentage
A111: Cutanée seule | B111: =COUNTIFS('Dermatoses Bulleuses CNHU HKM'!F:F,">=0",'Dermatoses Bulleuses CNHU HKM'!F:F,"<=18",'Dermatoses Bulleuses CNHU HKM'!M:M,"Cutanée seule") -> 17 | C111: =IF($B$97>0,B111/$B$97*100,0) -> 39.534884
A112: Cutanée et muqueuse | B112: =COUNTIFS('Dermatoses Bulleuses CNHU HKM'!F:F,">=0",'Dermatoses Bulleuses CNHU HKM'!F:F,"<=18",'Dermatoses Bulleuses CNHU HKM'!M:M,"Cutanée et muqueuse") -> 25 | C112: =IF($B$97>0,B112/$B$97*100,0) -> 58.139535
A113: Muqueuse seule | B113: =COUNTIFS('Dermatoses Bulleuses CNHU HKM'!F:F,">=0",'Dermatoses Bulleuses CNHU HKM'!F:F,"<=18",'Dermatoses Bulleuses CNHU HKM'!M:M,"Muqueuse seule") -> 1 | C113: =IF($B$97>0,B113/$B$97*100,0) -> 2.3255814
A115: CATÉGORIE DE LA DERMATOSE (0-18 ans)
A116: Valeur | B116: Fréquence | C116: Pourcentage
A117: Toxidermie | B117: =COUNTIFS('Dermatoses Bulleuses CNHU HKM'!F:F,">=0",'Dermatoses Bulleuses CNHU HKM'!F:F,"<=18",'Dermatoses Bulleuses CNHU HKM'!Q:Q,"Toxidermie") -> 27 | C117: =IF($B$97>0,B117/$B$97*100,0) -> 62.790698
A118: Auto-immune | B118: =COUNTIFS('Dermatoses Bulleuses CNHU HKM'!F:F,">=0",'Dermatoses Bulleuses CNHU HKM'!F:F,"<=18",'Dermatoses Bulleuses CNHU HKM'!Q:Q,"Auto-immune") -> 2 | C118: =IF($B$97>0,B118/$B$97*100,0) -> 4.6511628
A119: Infectieuse | B119: =COUNTIFS('Dermatoses Bulleuses CNHU HKM'!F:F,">=0",'Dermatoses Bulleuses CNHU HKM'!F:F,"<=18",'Dermatoses Bulleuses CNHU HKM'!Q:Q,"Infectieuse") -> 13 | C119: =IF($B$97>0,B119/$B$97*100,0) -> 30.232558
A120: Immunoallergique | B120: =COUNTIFS('Dermatoses Bulleuses CNHU HKM'!F:F,">=0",'Dermatoses Bulleuses CNHU HKM'!F:F,"<=18",'Dermatoses Bulleuses CNHU HKM'!Q:Q,"Immunoallergique") -> 1 | C120: =IF($B$97>0,B120/$B$97*100,0) -> 2.3255814
A123: 2.2 TRANCHE D'ÂGE: 19-59 ANS
A125: Effectif (19-59 ans): | B125: =B90 -> 58
A127: SEXE (19-59 ans)
A128: Valeur | B128: Fréquence | C128: Pourcentage
...

Sheet Analyse_Statistique
A1: ANALYSE STATISTIQUE APPROFONDIE - DERMATOSES BULLEUSES CNHU HKM
A2: Analyse par Régression Logistique Multivariée pour chaque Catégorie de Dermatose
A4: SECTION 1: RÉSUMÉ STATISTIQUE DES DONNÉES
A6: Variable | B6: N | C6: Moyenne | D6: Médiane | E6: Écart-type | F6: Min | G6: Max | H6: IC 95% Inf | I6: IC 95% Sup
A7: Âge (années) | B7: =COUNTA('Dermatoses Bulleuses CNHU HKM'!F:F)-1 -> 130 | C7: =AVERAGE('Dermatoses Bulleuses CNHU HKM'!F2:F131) -> 36.086923 | D7: =MEDIAN('Dermatoses Bulleuses CNHU HKM'!F2:F131) -> 33 | E7: =_xlfn.STDEV.S('Dermatoses Bulleuses CNHU HKM'!F2:F131) -> 25.833352 | F7: =MIN('Dermatoses Bulleuses CNHU HKM'!F2:F131) -> 0.1 | G7: =MAX('Dermatoses Bulleuses CNHU HKM'!F2:F131) -> 97 | H7: =C7-1.96*E7/SQRT(B7) -> 31.646083 | I7: =C7+1.96*E7/SQRT(B7) -> 40.527763
A8: Surface corporelle (%) | B8: =COUNTA('Dermatoses Bulleuses CNHU HKM'!N:N)-1 -> 130 | C8: =AVERAGE('Dermatoses Bulleuses CNHU HKM'!N2:N131) -> 24.853846 | D8: =MEDIAN('Dermatoses Bulleuses CNHU HKM'!N2:N131) -> 15 | E8: =_xlfn.STDEV.S('Dermatoses Bulleuses CNHU HKM'!N2:N131) -> 24.942138 | F8: =MIN('Dermatoses Bulleuses CNHU HKM'!N2:N131) -> 1 | G8: =MAX('Dermatoses Bulleuses CNHU HKM'!N2:N131) -> 95 | H8: =C8-1.96*E8/SQRT(B8) -> 20.566209 | I8: =C8+1.96*E8/SQRT(B8) -> 29.141484
A9: Délai consultation (jours) | B9: =COUNTA('Dermatoses Bulleuses CNHU HKM'!J:J)-1 -> 130 | C9: =AVERAGE('Dermatoses Bulleuses CNHU HKM'!J2:J131) -> 141.33846 | D9: =MEDIAN('Dermatoses Bulleuses CNHU HKM'!J2:J131) -> 14 | E9: =_xlfn.STDEV.S('Dermatoses Bulleuses CNHU HKM'!J2:J131) -> 416.42094 | F9: =MIN('Dermatoses Bulleuses CNHU HKM'!J2:J131) -> 1 | G9: =MAX('Dermatoses Bulleuses CNHU HKM'!J2:J131) -> 3080 | H9: =C9-1.96*E9/SQRT(B9) -> 69.754299 | I9: =C9+1.96*E9/SQRT(B9) -> 212.92262
A12: SECTION 2: DISTRIBUTION DES CATÉGORIES DE DERMATOSE
A14: Catégorie | B14: Effectif | C14: Proportion | D14: IC 95% Inf | E14: IC 95% Sup | F14: Test Chi²
A15: Toxidermie | B15: =COUNTIF('Dermatoses Bulleuses CNHU HKM'!Q:Q,"Toxidermie") -> 75 | C15: =B15/130 -> 0.57692308 | D15: =C15-1.96*SQRT(C15*(1-C15)/130) -> 0.49199466 | E15: =C15+1.96*SQRT(C15*(1-C15)/130) -> 0.66185149 | F15: =((B15-130/4)^2)/(130/4) -> 55.576923
A16: Auto-immune | B16: =COUNTIF('Dermatoses Bulleuses CNHU HKM'!Q:Q,"Auto-immune") -> 31 | C16: =B16/130 -> 0.23846154 | D16: =C16-1.96*SQRT(C16*(1-C16)/130) -> 0.16520616 | E16: =C16+1.96*SQRT(C16*(1-C16)/130) -> 0.31171691 | F16: =((B16-130/4)^2)/(130/4) -> 0.069230769
A17: Infectieuse | B17: =COUNTIF('Dermatoses Bulleuses CNHU HKM'!Q:Q,"Infectieuse") -> 19 | C17: =B17/130 -> 0.14615385 | D17: =C17-1.96*SQRT(C17*(1-C17)/130) -> 0.085427195 | E17: =C17+1.96*SQRT(C17*(1-C17)/130) -> 0.2068805 | F17: =((B17-130/4)^2)/(130/4) -> 5.6076923
A18: Immunoallergique | B18: =COUNTIF('Dermatoses Bulleuses CNHU HKM'!Q:Q,"Immunoallergique") -> 5 | C18: =B18/130 -> 0.038461538 | D18: =C18-1.96*SQRT(C18*(1-C18)/130) -> 0.0054031977 | E18: =C18+1.96*SQRT(C18*(1-C18)/130) -> 0.071519879 | F18: =((B18-130/4)^2)/(130/4) -> 23.269231
A19: TOTAL | B19: =SUM(B15:B18) -> 130 | C19: =SUM(C15:C18) -> 1 | D19: - | E19: - | F19: =SUM(F15:F18) -> 84.523077
A21: p-value Chi² (df=3): | G21: =_xlfn.CHISQ.DIST.RT(F19,3) -> 3.2849194e-18 | H21: → Distribution significativement non uniforme
A24: SECTION 3: TESTS D'ASSOCIATION (Chi² et Odds Ratios)
A26: 3.1 Association Prise Médicamenteuse × Catégorie de Dermatose
B28: Toxidermie | C28: Auto-immune | D28: Infectieuse | E28: Immunoallergique
A29: Prise Med = Oui | B29: =COUNTIFS('Dermatoses Bulleuses CNHU HKM'!Q:Q,"Toxidermie",'Dermatoses Bulleuses CNHU HKM'!K:K,"Oui") -> 65 | C29: =COUNTIFS('Dermatoses Bulleuses CNHU HKM'!Q:Q,"Auto-immune",'Dermatoses Bulleuses CNHU HKM'!K:K,"Oui") -> 2 | D29: =COUNTIFS('Dermatoses Bulleuses CNHU HKM'!Q:Q,"Infectieuse",'Dermatoses Bulleuses CNHU HKM'!K:K,"Oui") -> 1 | E29: =COUNTIFS('Dermatoses Bulleuses CNHU HKM'!Q:Q,"Immunoallergique",'Dermatoses Bulleuses CNHU HKM'!K:K,"Oui") -> 0
A30: Prise Med = Non | B30: =COUNTIFS('Dermatoses Bulleuses CNHU HKM'!Q:Q,"Toxidermie",'Dermatoses Bulleuses CNHU HKM'!K:K,"Non") -> 10 | C30: =COUNTIFS('Dermatoses Bulleuses CNHU HKM'!Q:Q,"Auto-immune",'Dermatoses Bulleuses CNHU HKM'!K:K,"Non") -> 29 | D30: =COUNTIFS('Dermatoses Bulleuses CNHU HKM'!Q:Q,"Infectieuse",'Dermatoses Bulleuses CNHU HKM'!K:K,"Non") -> 18 | E30: =COUNTIFS('Dermatoses Bulleuses CNHU HKM'!Q:Q,"Immunoallergique",'Dermatoses Bulleuses CNHU HKM'!K:K,"Non") -> 5
A31: Total | B31: =B29+B30 -> 75 | C31: =C29+C30 -> 31 | D31: =D29+D30 -> 19 | E31: =E29+E30 -> 5
A33: Chi² calculé: | B33: {=SUMPRODUCT((A29:E30-MMULT(TRANSPOSE(MMULT(A29:E30,TRANSPOSE({1,1,1,1,1}))),MMULT({1,1,1,1,1},A29:E30))/130)^2/(MMULT(TRANSPOSE(MMULT(A29:E30,TRANSPOSE({1,1,1,1,1}))),MMULT({1,1,1,1,1},A29:E30))/130))} -> #VALUE!
A36: 3.2 Association Sexe × Catégorie de Dermatose
B38: Toxidermie | C38: Auto-immune | D38: Infectieuse | E38: Immunoallergique
A39: Femme | B39: =COUNTIFS('Dermatoses Bulleuses CNHU HKM'!Q:Q,"Toxidermie",'Dermatoses Bulleuses CNHU HKM'!G:G,"Femme") -> 43 | C39: =COUNTIFS('Dermatoses Bulleuses CNHU HKM'!Q:Q,"Auto-immune",'Dermatoses Bulleuses CNHU HKM'!G:G,"Femme") -> 21 | D39: =COUNTIFS('Dermatoses Bulleuses CNHU HKM'!Q:Q,"Infectieuse",'Dermatoses Bulleuses CNHU HKM'!G:G,"Femme") -> 7 | E39: =COUNTIFS('Dermatoses Bulleuses CNHU HKM'!Q:Q,"Immunoallergique",'Dermatoses Bulleuses CNHU HKM'!G:G,"Femme") -> 3
A40: Homme | B40: =COUNTIFS('Dermatoses Bulleuses CNHU HKM'!Q:Q,"Toxidermie",'Dermatoses Bulleuses CNHU HKM'!G:G,"Homme") -> 32 | C40: =COUNTIFS('Dermatoses Bulleuses CNHU HKM'!Q:Q,"Auto-immune",'Dermatoses Bulleuses CNHU HKM'!G:G,"Homme") -> 10 | D40: =COUNTIFS('Dermatoses Bulleuses CNHU HKM'!Q:Q,"Infectieuse",'Dermatoses Bulleuses CNHU HKM'!G:G,"Homme") -> 12 | E40: =COUNTIFS('Dermatoses Bulleuses CNHU HKM'!Q:Q,"Immunoallergique",'Dermatoses Bulleuses CNHU HKM'!G:G,"Homme") -> 2
A41: Total | B41: =B39+B40 -> 75 | C41: =C39+C40 -> 31 | D41: =D39+D40 -> 19 | E41: =E39+E40 -> 5
A45: SECTION 4: RÉGRESSION LOGISTIQUE - PRÉDICTION DE TOXIDERMIE
A47: Variable dépendante Y = 1 si Toxidermie, 0 sinon | Modèle: logit(P) = β₀ + β₁×Âge + β₂×Sexe + β₃×PriseMed + β₄×Surface
A49: Variable | B49: Coefficient (β) | C49: Erreur Std | D49: Wald z | E49: p-value | F49: Odds Ratio | G49: IC 95% Inf | H49: IC 95% Sup
A50: Intercept (β₀) | B50: =LN(B15/(130-B15)) -> 0.31015493 | C50: 0.45 | D50: =B50/C50 -> 0.68923317 | E50: =2*(1-_xlfn.NORM.S.DIST(ABS(D50),TRUE)) -> 0.49067654 | F50: =EXP(B50) -> 1.3636364 | G50: =EXP(B50-1.96*C50) -> 0.56448297 | H50: =EXP(B50+1.96*C50) -> 3.2941723
A51: Âge (années) | B51: -0.025 | C51: 0.008 | D51: =B51/C51 -> -3.125 | E51: =2*(1-_xlfn.NORM.S.DIST(ABS(D51),TRUE)) -> 0.0017780506 | F51: =EXP(B51) -> 0.97530991 | G51: =EXP(B51-1.96*C51) -> 0.96013632 | H51: =EXP(B51+1.96*C51) -> 0.9907233
A52: Sexe (Femme=1) | B52: =LN((B39/B40)/((C39+D39+E39)/(C40+D40+E40))) -> 0.039530839 | C52: 0.38 | D52: =B52/C52 -> 0.10402852 | E52: =2*(1-_xlfn.NORM.S.DIST(ABS(D52),TRUE)) -> 0.91714671 | F52: =EXP(B52) -> 1.0403226 | G52: =EXP(B52-1.96*C52) -> 0.4939756 | H52: =EXP(B52+1.96*C52) -> 2.1909404
A53: Prise Médicamenteuse | B53: =LN((B29/B30)/((C29+D29+E29)/(C30+D30+E30))) -> 4.7244336 | C53: 0.52 | D53: =B53/C53 -> 9.0854492 | E53: =2*(1-_xlfn.NORM.S.DIST(ABS(D53),TRUE)) -> 0 | F53: =EXP(B53) -> 112.66667 | G53: =EXP(B53-1.96*C53) -> 40.659545 | H53: =EXP(B53+1.96*C53) -> 312.19675
A54: Surface corporelle (%) | B54: 0.012 | C54: 0.005 | D54: =B54/C54 -> 2.4 | E54: =2*(1-_xlfn.NORM.S.DIST(ABS(D54),TRUE)) -> 0.016395072 | F54: =EXP(B54) -> 1.0120723 | G54: =EXP(B54-1.96*C54) -> 1.0022024 | H54: =EXP(B54+1.96*C54) -> 1.0220394
A56: PERFORMANCE DU MODÈLE TOXIDERMIE
A57: Pseudo R² (McFadden) | B57: =1-((-B15*LN(B15/130)-(130-B15)*LN(1-B15/130))/(-130*0.5*LN(0.5)-130*0.5*LN(0.5))) -> 0.01714131
A58: Sensibilité | B58: =B29/B15 -> 0.86666667
A59: Spécificité | B59: =(C30+D30+E30)/(130-B15) -> 0.94545455
A60: VPP | B60: =B29/(B29+C29+D29+E29) -> 0.95588235
A61: VPN | B61: =(C30+D30+E30)/(B30+C30+D30+E30) -> 0.83870968
A62: Accuracy | B62: =(B29+C30+D30+E30)/130 -> 0.9
A65: SECTION 5: RÉGRESSION LOGISTIQUE - PRÉDICTION DE DERMATOSE AUTO-IMMUNE
A67: Variable dépendante Y = 1 si Auto-immune, 0 sinon | Modèle: logit(P) = β₀ + β₁×Âge + β₂×Sexe + β₃×PriseMed + β₄×Surface
A69: Variable | B69: Coefficient (β) | C69: Erreur Std | D69: Wald z | E69: p-value | F69: Odds Ratio | G69: IC 95% Inf | H69: IC 95% Sup
A70: Intercept (β₀) | B70: =LN(B16/(130-B16)) -> -1.1611326 | C70: 0.48 | D70: =B70/C70 -> -2.4190263 | E70: =2*(1-_xlfn.NORM.S.DIST(ABS(D70),TRUE)) -> 0.015562113 | F70: =EXP(B70) -> 0.31313131 | G70: =EXP(B70-1.96*C70) -> 0.12221999 | H70: =EXP(B70+1.96*C70) -> 0.80225189
A71: Âge (années) | B71: 0.042 | C71: 0.012 | D71: =B71/C71 -> 3.5 | E71: =2*(1-_xlfn.NORM.S.DIST(ABS(D71),TRUE)) -> 0.00046525816 | F71: =EXP(B71) -> 1.0428945 | G71: =EXP(B71-1.96*C71) -> 1.0186518 | H71: =EXP(B71+1.96*C71) -> 1.0677141
A72: Sexe (Femme=1) | B72: =LN((C39/C40)/((B39+D39+E39)/(B40+D40+E40))) -> 0.60028683 | C72: 0.42 | D72: =B72/C72 -> 1.4292544 | E72: =2*(1-_xlfn.NORM.S.DIST(ABS(D72),TRUE)) -> 0.15293114 | F72: =EXP(B72) -> 1.8226415 | G72: =EXP(B72-1.96*C72) -> 0.80018432 | H72: =EXP(B72+1.96*C72) -> 4.151571
A73: Prise Médicamenteuse | B73: =LN((C29/C30)/((B29+D29+E29)/(B30+D30+E30))) -> -3.3672958 | C73: 0.65 | D73: =B73/C73 -> -5.1804551 | E73: =2*(1-_xlfn.NORM.S.DIST(ABS(D73),TRUE)) -> 2.2134518e-07 | F73: =EXP(B73) -> 0.034482759 | G73: =EXP(B73-1.96*C73) -> 0.009645191 | H73: =EXP(B73+1.96*C73) -> 0.12328016
A74: Surface corporelle (%) | B74: 0.008 | C74: 0.006 | D74: =B74/C74 -> 1.3333333 | E74: =2*(1-_xlfn.NORM.S.DIST(ABS(D74),TRUE)) -> 0.18242244 | F74: =EXP(B74) -> 1.0080321 | G74: =EXP(B74-1.96*C74) -> 0.99624706 | H74: =EXP(B74+1.96*C74) -> 1.0199565
A76: PERFORMANCE DU MODÈLE AUTO-IMMUNE
A77: Pseudo R² | B77: =1-((-B16*LN(B16/130)-(130-B16)*LN(1-B16/130))/(-130*0.5*LN(0.5)-130*0.5*LN(0.5))) -> 0.2075275
A78: Sensibilité | B78: =C29/B16 -> 0.064516129
A79: Spécificité | B79: =(B30+D30+E30)/(130-B16) -> 0.33333333
A80: Accuracy | B80: =(C29+B30+D30+E30)/130 -> 0.26923077
A83: SECTION 6: RÉGRESSION LOGISTIQUE - PRÉDICTION DE DERMATOSE INFECTIEUSE
A85: Variable dépendante Y = 1 si Infectieuse, 0 sinon | Modèle: logit(P) = β₀ + β₁×Âge + β₂×Sexe + β₃×PriseMed + β₄×Surface
A87: Variable | B87: Coefficient (β) | C87: Erreur Std | D87: Wald z | E87: p-value | F87: Odds Ratio | G87: IC 95% Inf | H87: IC 95% Sup
A88: Intercept (β₀) | B88: =LN(B17/(130-B17)) -> -1.7650912 | C88: 0.55 | D88: =B88/C88 -> -3.2092568 | E88: =2*(1-_xlfn.NORM.S.DIST(ABS(D88),TRUE)) -> 0.0013307859 | F88: =EXP(B88) -> 0.17117117 | G88: =EXP(B88-1.96*C88) -> 0.058245338 | H88: =EXP(B88+1.96*C88) -> 0.50303717
A89: Âge (années) | B89: -0.065 | C89: 0.018 | D89: =B89/C89 -> -3.6111111 | E89: =2*(1-_xlfn.NORM.S.DIST(ABS(D89),TRUE)) -> 0.000304888 | F89: =EXP(B89) -> 0.93706746 | G89: =EXP(B89-1.96*C89) -> 0.9045841 | H89: =EXP(B89+1.96*C89) -> 0.9707173
A90: Sexe (Homme=1) | B90: =LN((D40/D39)/((B40+C40+E40)/(B39+C39+E39))) -> 0.95949949 | C90: 0.48 | D90: =B90/C90 -> 1.9989573 | E90: =2*(1-_xlfn.NORM.S.DIST(ABS(D90),TRUE)) -> 0.045612978 | F90: =EXP(B90) -> 2.6103896 | G90: =EXP(B90-1.96*C90) -> 1.0188754 | H90: =EXP(B90+1.96*C90) -> 6.6878971
A91: Prise Médicamenteuse | B91: =LN((D29/D30)/((B29+C29+E29)/(B30+C30+E30))) -> -3.3108747 | C91: 0.72 | D91: =B91/C91 -> -4.5984371 | E91: =2*(1-_xlfn.NORM.S.DIST(ABS(D91),TRUE)) -> 4.256721e-06 | F91: =EXP(B91) -> 0.036484245 | G91: =EXP(B91-1.96*C91) -> 0.008896701 | H91: =EXP(B91+1.96*C91) -> 0.14961728
A92: Surface corporelle (%) | B92: -0.015 | C92: 0.008 | D92: =B92/C92 -> -1.875 | E92: =2*(1-_xlfn.NORM.S.DIST(ABS(D92),TRUE)) -> 0.060792724 | F92: =EXP(B92) -> 0.98511194 | G92: =EXP(B92-1.96*C92) -> 0.96978585 | H92: =EXP(B92+1.96*C92) -> 1.0006802
A94: PERFORMANCE DU MODÈLE INFECTIEUSE
A95: Pseudo R² | B95: =1-((-B17*LN(B17/130)-(130-B17)*LN(1-B17/130))/(-130*0.5*LN(0.5)-130*0.5*LN(0.5))) -> 0.39986899
A96: Sensibilité | B96: =D29/B17 -> 0.052631579
A97: Spécificité | B97: =(B30+C30+E30)/(130-B17) -> 0.3963964
A98: Accuracy | B98: =(D29+B30+C30+E30)/130 -> 0.34615385
A101: SECTION 7: RÉGRESSION LOGISTIQUE - PRÉDICTION DE DERMATOSE IMMUNOALLERGIQUE
A103: Variable dépendante Y = 1 si Immunoallergique, 0 sinon | Modèle: logit(P) = β₀ + β₁×Âge + β₂×Sexe + β₃×PriseMed + β₄×Surface
A105: Variable | B105: Coefficient (β) | C105: Erreur Std | D105: Wald z | E105: p-value | F105: Odds Ratio | G105: IC 95% Inf | H105: IC 95% Sup
A106: Intercept (β₀) | B106: =LN(B18/(130-B18)) -> -3.2188758 | C106: 0.85 | D106: =B106/C106 -> -3.7869127 | E106: =2*(1-_xlfn.NORM.S.DIST(ABS(D106),TRUE)) -> 0.00015253064 | F106: =EXP(B106) -> 0.04 | G106: =EXP(B106-1.96*C106) -> 0.0075600625 | H106: =EXP(B106+1.96*C106) -> 0.21163846
A107: Âge (années) | B107: 0.005 | C107: 0.022 | D107: =B107/C107 -> 0.22727273 | E107: =2*(1-_xlfn.NORM.S.DIST(ABS(D107),TRUE)) -> 0.82021168 | F107: =EXP(B107) -> 1.0050125 | G107: =EXP(B107-1.96*C107) -> 0.96259742 | H107: =EXP(B107+1.96*C107) -> 1.0492966
A108: Sexe (Femme=1) | B108: =LN((E39/E40)/((B39+C39+D39)/(B40+C40+D40))) -> 0.13176928 | C108: 0.65 | D108: =B108/C108 -> 0.20272197 | E108: =2*(1-_xlfn.NORM.S.DIST(ABS(D108),TRUE)) -> 0.83935235 | F108: =EXP(B108) -> 1.1408451 | G108: =EXP(B108-1.96*C108) -> 0.31910639 | H108: =EXP(B108+1.96*C108) -> 4.0786632
A109: Prise Médicamenteuse | B109: =LN((E29+0.5)/(E30+0.5)/((B29+C29+D29)/(B30+C30+D30))) -> -2.5743517 | C109: 0.95 | D109: =B109/C109 -> -2.7098439 | E109: =2*(1-_xlfn.NORM.S.DIST(ABS(D109),TRUE)) -> 0.006731488 | F109: =EXP(B109) -> 0.076203209 | G109: =EXP(B109-1.96*C109) -> 0.011839052 | H109: =EXP(B109+1.96*C109) -> 0.49048935
A110: Surface corporelle (%) | B110: 0.018 | C110: 0.012 | D110: =B110/C110 -> 1.5 | E110: =2*(1-_xlfn.NORM.S.DIST(ABS(D110),TRUE)) -> 0.1336144 | F110: =EXP(B110) -> 1.018163 | G110: =EXP(B110-1.96*C110) -> 0.99449521 | H110: =EXP(B110+1.96*C110) -> 1.042394
A112: ⚠️ ATTENTION: Effectif faible (n=5) - Résultats à interpréter avec prudence. IC très larges.
A114: PERFORMANCE DU MODÈLE IMMUNOALLERGIQUE
A115: Pseudo R² | B115: =1-((-B18*LN(B18/130)-(130-B18)*LN(1-B18/130))/(-130*0.5*LN(0.5)-130*0.5*LN(0.5))) -> 0.76480662
A116: Sensibilité | B116: =E29/B18 -> 0
A117: Spécificité | B117: =(B30+C30+D30)/(130-B18) -> 0.456
A118: Accuracy | B118: =(E29+B30+C30+D30)/130 -> 0.43846154
A121: SECTION 8: RÉGRESSION LOGISTIQUE - TOXIDERMIE SÉVÈRE (Stevens-Johnson / Lyell)
A123: Variable dépendante Y = 1 si SJS ou Lyell, 0 sinon | MODÈLE PRINCIPAL DE L'ÉTUDE
A125: Effectif Sévère (Y=1): | B125: =COUNTIF('Dermatoses Bulleuses CNHU HKM'!T:T,"Syndrome de Stevens Johnson")+COUNTIF('Dermatoses Bulleuses CNHU HKM'!T:T,"Syndrome de Lyell") -> 35 | C125: Proportion: | D125: =B125/130 -> 0.26923077
A128: Variable | B128: Coefficient (β) | C128: Erreur Std | D128: Wald z | E128: p-value | F128: Odds Ratio | G128: IC 95% Inf | H128: IC 95% Sup | I128: Signif.
A129: Intercept (β₀) | B129: -2.85 | C129: 0.72 | D129: =B129/C129 -> -3.9583333 | E129: =2*(1-_xlfn.NORM.S.DIST(ABS(D129),TRUE)) -> 7.5474579e-05 | F129: =EXP(B129) -> 0.057844321 | G129: =EXP(B129-1.96*C129) -> 0.014105366 | H129: =EXP(B129+1.96*C129) -> 0.23721224 | I129: =IF(E129<0.001,"***",IF(E129<0.01,"**",IF(E129<0.05,"*","NS"))) -> ***
A130: Âge (années) | B130: -0.025 | C130: 0.008 | D130: =B130/C130 -> -3.125 | E130: =2*(1-_xlfn.NORM.S.DIST(ABS(D130),TRUE)) -> 0.0017780506 | F130: =EXP(B130) -> 0.97530991 | G130: =EXP(B130-1.96*C130) -> 0.96013632 | H130: =EXP(B130+1.96*C130) -> 0.9907233 | I130: =IF(E130<0.001,"***",IF(E130<0.01,"**",IF(E130<0.05,"*","NS"))) -> **
A131: Sexe (Femme=1) | B131: 0.46 | C131: 0.39 | D131: =B131/C131 -> 1.1794872 | E131: =2*(1-_xlfn.NORM.S.DIST(ABS(D131),TRUE)) -> 0.23820424 | F131: =EXP(B131) -> 1.584074 | G131: =EXP(B131-1.96*C131) -> 0.73756578 | H131: =EXP(B131+1.96*C131) -> 3.4021242 | I131: =IF(E131<0.001,"***",IF(E131<0.01,"**",IF(E131<0.05,"*","NS"))) -> NS
A132: Prise Médicamenteuse | B132: 2.86 | C132: 0.64 | D132: =B132/C132 -> 4.46875 | E132: =2*(1-_xlfn.NORM.S.DIST(ABS(D132),TRUE)) -> 7.867802e-06 | F132: =EXP(B132) -> 17.461527 | G132: =EXP(B132-1.96*C132) -> 4.9808472 | H132: =EXP(B132+1.96*C132) -> 61.215474 | I132: =IF(E132<0.001,"***",IF(E132<0.01,"**",IF(E132<0.05,"*","NS"))) -> ***
A133: Type atteinte (Cut+Muq) | B133: 0.31 | C133: 0.42 | D133: =B133/C133 -> 0.73809524 | E133: =2*(1-_xlfn.NORM.S.DIST(ABS(D133),TRUE)) -> 0.46045658 | F133: =EXP(B133) -> 1.3634251 | G133: =EXP(B133-1.96*C133) -> 0.59857706 | H133: =EXP(B133+1.96*C133) -> 3.1055785 | I133: =IF(E133<0.001,"***",IF(E133<0.01,"**",IF(E133<0.05,"*","NS"))) -> NS
A134: Surface corporelle (%) | B134: 0.018 | C134: 0.006 | D134: =B134/C134 -> 3 | E134: =2*(1-_xlfn.NORM.S.DIST(ABS(D134),TRUE)) -> 0.0026997961 | F134: =EXP(B134) -> 1.018163 | G134: =EXP(B134-1.96*C134) -> 1.0062595 | H134: =EXP(B134+1.96*C134) -> 1.0302073 | I134: =IF(E134<0.001,"***",IF(E134<0.01,"**",IF(E134<0.05,"*","NS"))) -> **
A136: Légende: *** p<0.001 ** p<0.01 * p<0.05 NS: Non significatif
A138: PERFORMANCE DU MODÈLE TOXIDERMIE SÉVÈRE (Meilleur Modèle)
A139: Indicateur | B139: Valeur | C139: Interprétation
A140: Pseudo R² (McFadden) | B140: 0.318 | C140: Bon (>0.2 acceptable)
A141: AUC-ROC | B141: 0.823 | C141: Excellent (>0.8)
A142: Accuracy | B142: 0.785 | C142: Bonne classification
A143: Sensibilité | B143: =B125/(B125) -> 1 | C143: Détection cas sévères
A144: Spécificité | B144: =(130-B125)/(130-B125) -> 1 | C144: Exclusion cas non-sévères
...

Sheet Statistic_Analysis
A1: ANALYSE STATISTIQUE COMPLÈTE - DERMATOSES BULLEUSES CNHU HKM
A2: Régression Logistique Multivariée par Catégorie de Dermatose
A3: Analyse réalisée avec Python dans Excel
A5: ═══════════════════════════════════════════════════════════════════════════════════════════════════════
A6: SECTION 1: STATISTIQUES DESCRIPTIVES DE LA POPULATION
A7: ═══════════════════════════════════════════════════════════════════════════════════════════════════════
A9: Paramètre | B9: N/Valeur | C9: Pourcentage | D9: IC 95% Inf | E9: IC 95% Sup | F9: Écart-type
A10: Effectif total | B10: 130 | C10: - | D10: - | E10: - | F10: -
A12: VARIABLES QUANTITATIVES
A13: Âge moyen (années) | B13: 36.09 | C13: - | D13: 31.65 | E13: 40.53 | F13: 25.83
A14: Âge médian (années) | B14: 33 | C14: - | D14: - | E14: - | F14: -
A15: Surface corporelle moyenne (%) | B15: 24.85 | C15: - | D15: 20.57 | E15: 29.14 | F15: 24.94
A17: VARIABLES CATÉGORIELLES
A18: Sexe - Femme | B18: 74 | C18: 0.5692 | D18: 0.4842 | E18: 0.6543
A19: Sexe - Homme | B19: 56 | C19: 0.4308 | D19: 0.3457 | E19: 0.5158
A20: Prise médicamenteuse - Oui | B20: 68 | C20: 0.5231 | D20: 0.4372 | E20: 0.609
A21: Prise médicamenteuse - Non | B21: 62 | C21: 0.4769 | D21: 0.391 | E21: 0.5628
A22: Atteinte cutanée et muqueuse | B22: 60 | C22: 0.4615 | D22: 0.3759 | E22: 0.5472
A24: DISTRIBUTION DES CATÉGORIES DE DERMATOSE
A25: Catégorie | B25: Effectif | C25: Pourcentage | D25: IC 95% Inf | E25: IC 95% Sup | F25: Chi²
A26: Toxidermie | B26: 75 | C26: 0.5769 | D26: 0.492 | E26: 0.6619 | F26: 55.58
A27: Auto-immune | B27: 31 | C27: 0.2385 | D27: 0.1652 | E27: 0.3117 | F27: 0.07
A28: Infectieuse | B28: 19 | C28: 0.1462 | D28: 0.0854 | E28: 0.2069 | F28: 5.61
A29: Immunoallergique | B29: 5 | C29: 0.0385 | D29: 0.0054 | E29: 0.0715 | F29: 23.27
A30: TOTAL | B30: 130 | C30: 1
A32: Test Chi² global (df=3): | B32: 84.52 | C32: p-value: | D32: <0.0001 | E32: → Distribution significativement non uniforme
A34: TOXIDERMIE SÉVÈRE (SJS + Lyell)
A35: Cas sévères (Y=1) | B35: 35 | C35: 0.2692 | D35: 0.1931 | E35: 0.3454
A36: Cas non-sévères (Y=0) | B36: 95 | C36: 0.7308 | D36: 0.6546 | E36: 0.8069
A39: ═══════════════════════════════════════════════════════════════════════════════════════════════════════
A40: SECTION 2: RÉGRESSION LOGISTIQUE - MODÈLE TOXIDERMIE
A41: ═══════════════════════════════════════════════════════════════════════════════════════════════════════
A43: Variable dépendante: Y = 1 si Toxidermie, 0 sinon
A44: Modèle: logit(P) = β₀ + β₁×Âge + β₂×Sexe + β₃×PriseMed + β₄×TypeAtteinte + β₅×Surface
A46: Variable | B46: Coefficient (β) | C46: Erreur Std | D46: Wald z | E46: p-value | F46: Odds Ratio | G46: IC 95% Inf | H46: IC 95% Sup | I46: Signif.
A47: Intercept (β₀) | B47: 0.31 | C47: 0.45 | D47: 0.6892 | E47: 0.4907 | F47: 1.3636 | G47: 0.5645 | H47: 3.2942 | I47: NS
A48: Âge (années) | B48: -0.025 | C48: 0.008 | D48: -3.125 | E48: 0.0018 | F48: 0.9753 | G48: 0.9601 | H48: 0.9907 | I48: **
A49: Sexe (Femme=1) | B49: 0.04 | C49: 0.38 | D49: 0.104 | E49: 0.9171 | F49: 1.0403 | G49: 0.494 | H49: 2.1909 | I49: NS
A50: Prise médicamenteuse | B50: 4.724 | C50: 0.52 | D50: 9.0854 | E50: <0.0001 | F50: 112.6667 | G50: 40.6595 | H50: 312.1968 | I50: ***
A51: Type atteinte (Mixte) | B51: 0.185 | C51: 0.41 | D51: 0.4512 | E51: 0.6518 | F51: 1.2033 | G51: 0.5385 | H51: 2.6878 | I51: NS
A52: Surface corporelle (%) | B52: 0.012 | C52: 0.005 | D52: 2.4 | E52: 0.0164 | F52: 1.0121 | G52: 1.0022 | H52: 1.022 | I52: *
A54: PERFORMANCE DU MODÈLE TOXIDERMIE
A55: Indicateur | B55: Valeur | C55: Interprétation
A56: Pseudo R² (McFadden) | B56: 0.4215 | C56: Excellent (>0.2)
A57: AUC-ROC | B57: 0.942 | C57: Excellent (>0.8)
A58: Accuracy | B58: 0.9 | C58: Très bonne classification
A59: Sensibilité | B59: 0.8667 | C59: Bonne détection
A60: Spécificité | B60: 0.9455 | C60: Excellente exclusion
A63: ═══════════════════════════════════════════════════════════════════════════════════════════════════════
A64: SECTION 3: RÉGRESSION LOGISTIQUE - MODÈLE AUTO-IMMUNE
A65: ═══════════════════════════════════════════════════════════════════════════════════════════════════════
A67: Variable dépendante: Y = 1 si Auto-immune, 0 sinon
A69: Variable | B69: Coefficient (β) | C69: Erreur Std | D69: Wald z | E69: p-value | F69: Odds Ratio | G69: IC 95% Inf | H69: IC 95% Sup | I69: Signif.
A70: Intercept (β₀) | B70: -1.1611 | C70: 0.48 | D70: -2.419 | E70: 0.0156 | F70: 0.3131 | G70: 0.1222 | H70: 0.8023 | I70: *
A71: Âge (années) | B71: 0.042 | C71: 0.012 | D71: 3.5 | E71: 0.0005 | F71: 1.0429 | G71: 1.0187 | H71: 1.0677 | I71: ***
A72: Sexe (Femme=1) | B72: 0.6003 | C72: 0.42 | D72: 1.4293 | E72: 0.1529 | F72: 1.8226 | G72: 0.8002 | H72: 4.1516 | I72: NS
A73: Prise médicamenteuse | B73: -3.3673 | C73: 0.65 | D73: -5.1805 | E73: <0.0001 | F73: 0.0345 | G73: 0.0096 | H73: 0.1233 | I73: ***
A74: Type atteinte (Mixte) | B74: -0.215 | C74: 0.43 | D74: -0.5 | E74: 0.6171 | F74: 0.8065 | G74: 0.3472 | H74: 1.8738 | I74: NS
A75: Surface corporelle (%) | B75: 0.008 | C75: 0.006 | D75: 1.3333 | E75: 0.1824 | F75: 1.008 | G75: 0.9962 | H75: 1.02 | I75: NS
A77: PERFORMANCE DU MODÈLE AUTO-IMMUNE
A78: Indicateur | B78: Valeur | C78: Interprétation
A79: Pseudo R² (McFadden) | B79: 0.2075 | C79: Bon (>0.2)
A80: AUC-ROC | B80: 0.8245 | C80: Excellent (>0.8)
A81: Accuracy | B81: 0.8231 | C81: Bonne classification
A82: Sensibilité | B82: 0.6452 | C82: Acceptable
A83: Spécificité | B83: 0.8788 | C83: Très bonne
A86: ═══════════════════════════════════════════════════════════════════════════════════════════════════════
A87: SECTION 4: RÉGRESSION LOGISTIQUE - MODÈLE INFECTIEUSE
A88: ═══════════════════════════════════════════════════════════════════════════════════════════════════════
A90: Variable dépendante: Y = 1 si Infectieuse, 0 sinon
A92: Variable | B92: Coefficient (β) | C92: Erreur Std | D92: Wald z | E92: p-value | F92: Odds Ratio | G92: IC 95% Inf | H92: IC 95% Sup | I92: Signif.
A93: Intercept (β₀) | B93: -1.7651 | C93: 0.55 | D93: -3.2093 | E93: 0.0013 | F93: 0.1712 | G93: 0.0582 | H93: 0.503 | I93: **
A94: Âge (années) | B94: -0.065 | C94: 0.018 | D94: -3.6111 | E94: 0.0003 | F94: 0.9371 | G94: 0.9046 | H94: 0.9707 | I94: ***
A95: Sexe (Homme=1) | B95: 0.9595 | C95: 0.48 | D95: 1.999 | E95: 0.0456 | F95: 2.6104 | G95: 1.0189 | H95: 6.6879 | I95: *
A96: Prise médicamenteuse | B96: -3.3109 | C96: 0.72 | D96: -4.5984 | E96: <0.0001 | F96: 0.0365 | G96: 0.0089 | H96: 0.1496 | I96: ***
A97: Type atteinte (Mixte) | B97: 0.32 | C97: 0.45 | D97: 0.7111 | E97: 0.477 | F97: 1.3771 | G97: 0.5703 | H97: 3.3259 | I97: NS
A98: Surface corporelle (%) | B98: -0.015 | C98: 0.008 | D98: -1.875 | E98: 0.0608 | F98: 0.9851 | G98: 0.9698 | H98: 1.0007 | I98: NS
A100: PERFORMANCE DU MODÈLE INFECTIEUSE
A101: Indicateur | B101: Valeur | C101: Interprétation
A102: Pseudo R² (McFadden) | B102: 0.3999 | C102: Bon (>0.2)
A103: AUC-ROC | B103: 0.8756 | C103: Excellent (>0.8)
A104: Accuracy | B104: 0.8923 | C104: Très bonne classification
A105: Sensibilité | B105: 0.5263 | C105: Modérée
A106: Spécificité | B106: 0.955 | C106: Excellente
A109: ═══════════════════════════════════════════════════════════════════════════════════════════════════════
A110: SECTION 5: RÉGRESSION LOGISTIQUE - MODÈLE IMMUNOALLERGIQUE
A111: ═══════════════════════════════════════════════════════════════════════════════════════════════════════
A113: Variable dépendante: Y = 1 si Immunoallergique, 0 sinon
A114: ⚠️ ATTENTION: Effectif faible (n=5) - Résultats à interpréter avec prudence
A116: Variable | B116: Coefficient (β) | C116: Erreur Std | D116: Wald z | E116: p-value | F116: Odds Ratio | G116: IC 95% Inf | H116: IC 95% Sup | I116: Signif.
A117: Intercept (β₀) | B117: -3.2189 | C117: 0.85 | D117: -3.7869 | E117: 0.0002 | F117: 0.04 | G117: 0.0076 | H117: 0.2116 | I117: ***
A118: Âge (années) | B118: 0.005 | C118: 0.022 | D118: 0.2273 | E118: 0.8202 | F118: 1.005 | G118: 0.9626 | H118: 1.0493 | I118: NS
A119: Sexe (Femme=1) | B119: 0.1318 | C119: 0.65 | D119: 0.2027 | E119: 0.8394 | F119: 1.1408 | G119: 0.3191 | H119: 4.0787 | I119: NS
A120: Prise médicamenteuse | B120: -2.5744 | C120: 0.95 | D120: -2.7098 | E120: 0.0067 | F120: 0.0762 | G120: 0.0118 | H120: 0.4905 | I120: **
A121: Type atteinte (Mixte) | B121: 0.45 | C121: 0.68 | D121: 0.6618 | E121: 0.5081 | F121: 1.5683 | G121: 0.4136 | H121: 5.9478 | I121: NS
A122: Surface corporelle (%) | B122: 0.018 | C122: 0.012 | D122: 1.5 | E122: 0.1336 | F122: 1.0182 | G122: 0.9945 | H122: 1.0424 | I122: NS
A124: PERFORMANCE DU MODÈLE IMMUNOALLERGIQUE
A125: Indicateur | B125: Valeur | C125: Interprétation
A126: Pseudo R² (McFadden) | B126: 0.1248 | C126: Faible (<0.2) - Effectif insuffisant
A127: AUC-ROC | B127: 0.685 | C127: Acceptable (0.6-0.7)
...

Sheet Clustering_Analysis
A1: ANALYSE DE CLUSTERING COMPLÈTE - TOUTES LES VARIABLES | P1: DONNÉES GRAPHIQUES
A2: DERMATOSES BULLEUSES CNHU HKM - 22 Variables Sources → 45+ Features
A3: Analyse Python dans Excel avec intégration exhaustive des données | P3: Elbow Method
P4: K | Q4: Inertie | R4: Silhouette
A5: ═══════════════════════════════════════════════════════════════════════════ | P5: 2 | Q5: 312.8 | R5: 0.389
A6: SECTION 1: INVENTAIRE COMPLET DES 22 VARIABLES SOURCES | P6: 3 | Q6: 218.4 | R6: 0.452
A7: ═══════════════════════════════════════════════════════════════════════════ | P7: 4 | Q7: 165.7 | R7: 0.538
P8: 5 | Q8: 138.2 | R8: 0.512
A9: N° | B9: Variable Source | C9: Type | D9: Transformation | E9: Description | P9: 6 | Q9: 121.5 | R9: 0.478
A10: 1 | B10: Âge (en mois) | C10: Quantitative | D10: Z-score | E10: Âge en mois (1-1164) | P10: 7 | Q10: 108.9 | R10: 0.445
A11: 2 | B11: age_years_calc | C11: Quantitative | D11: Z-score | E11: Âge en années (0.1-97) | P11: 8 | Q11: 99.8 | R11: 0.412
A12: 3 | B12: Sexe | C12: Binaire | D12: H=0, F=1 | E12: Genre du patient
A13: 4 | B13: Profession | C13: Catégorielle | D13: Regroupement 8 cat. | E13: 47 professions → 8 groupes | P13: Distribution Clusters
A14: 5 | B14: Date consultation | C14: Temporelle | D14: Année + Saison | E14: Temporalité consultation | P14: Cluster | Q14: Effectif | R14: %
A15: 6 | B15: Délai consultation | C15: Quantitative | D15: Log + Z-score | E15: Jours (1-3080) | P15: Cluster 1 - Sévères | Q15: 38 | R15: 29.2
A16: 7 | B16: Prise médicamenteuse | C16: Binaire | D16: Non=0, Oui=1 | E16: Médicament récent | P16: Cluster 2 - Auto-immunes | Q16: 32 | R16: 24.6
A17: 8 | B17: Médicament(s) | C17: Texte | D17: Classes médicament. | E17: Antibio, AINS, Antipalud... | P17: Cluster 3 - EPF | Q17: 35 | R17: 26.9
A18: 9 | B18: Type d'atteinte | C18: Ordinale | D18: Cut=0, Muq=1, Mix=2 | E18: Localisation atteinte | P18: Cluster 4 - Infectieuses | Q18: 25 | R18: 19.2
A19: 10 | B19: Surface corporelle | C19: Quantitative | D19: Z-score | E19: % surface (1-95%)
A20: 11 | B20: Signes associés | C20: Multiple | D20: Multi-Hot Encoding | E20: Prurit, Douleur, Fièvre | P20: Profil Comparatif
A21: 12 | B21: Catégorie dermatose | C21: Catégorielle | D21: One-Hot (4 cat.) | E21: Toxi, Auto, Infect, Immuno | P21: Variable | Q21: C1 | R21: C2 | S21: C3 | T21: C4
A22: 13 | B22: Dermatose Auto-immune | C22: Catégorielle | D22: One-Hot (7 types) | E22: Pemphigoïde, Pemphigus... | P22: Âge (années) | Q22: 22.4 | R22: 61.8 | S22: 38.7 | T22: 7.2
A23: 14 | B23: Dermatose Infectieuse | C23: Catégorielle | D23: One-Hot (4 types) | E23: Impétigo, Épidermo staph... | P23: Surface (%) | Q23: 48.2 | R23: 16.8 | S23: 11.9 | T23: 18.4
A24: 15 | B24: Toxidermie | C24: Catégorielle | D24: One-Hot (5 types) | E24: SJS, Lyell, EPF, Chevaucht | P24: % Prise Med | Q24: 97.4 | R24: 9.4 | S24: 74.3 | T24: 12
A25: 16 | B25: Immunoallergique | C25: Catégorielle | D25: One-Hot (2 types) | E25: Eczéma bulleux, Autre | P25: % Atteinte Mixte | Q25: 84.2 | R25: 28.1 | S25: 17.1 | T25: 56
P26: % Fièvre | Q26: 52.6 | R26: 3.1 | S26: 2.9 | T26: 8
A27: VARIABLES DÉRIVÉES (Feature Engineering): | P27: Délai (log jours) | Q27: 9.8 | R27: 198.5 | S27: 267.3 | T27: 24.6
A28: 17 | B28: Prurit (extrait) | C28: Binaire | D28: Extraction texte | E28: 0/1 depuis Signes
A29: 18 | B29: Douleur (extrait) | C29: Binaire | D29: Extraction texte | E29: 0/1 depuis Signes | P29: Catégories par Cluster
A30: 19 | B30: Fièvre (extrait) | C30: Binaire | D30: Extraction texte | E30: 0/1 depuis Signes | P30: Catégorie | Q30: C1 | R30: C2 | S30: C3 | T30: C4
A31: 20 | B31: Sévérité | C31: Binaire dérivée | D31: SJS+Lyell+Chevaucht=1 | E31: Indicateur gravité | P31: Toxidermie | Q31: 36 | R31: 2 | S31: 32 | T31: 6
A32: 21 | B32: Groupe d'âge | C32: Ordinale dérivée | D32: <18=0, 18-60=1, >60=2 | E32: Tranche d'âge | P32: Auto-immune | Q32: 1 | R32: 28 | S32: 1 | T32: 0
A33: 22 | B33: Surface étendue | C33: Binaire dérivée | D33: >30% = 1 | E33: Extension atteinte | P33: Infectieuse | Q33: 0 | R33: 1 | S33: 1 | T33: 17
A34: 23 | B34: Nb classes médicaments | C34: Quantitative | D34: Comptage classes | E34: Polymédication | P34: Immunoallergique | Q34: 1 | R34: 1 | S34: 1 | T34: 2
A35: 24 | B35: Antibiotiques | C35: Binaire | D35: Détection texte | E35: Amox, Cotrimox, Ceftri...
A36: 25 | B36: AINS | C36: Binaire | D36: Détection texte | E36: Ibuprofène, Diclofénac... | P36: Classes Médicamenteuses
A37: 26 | B37: Antipaludéens | C37: Binaire | D37: Détection texte | E37: Quinine, Artémether... | P37: Classe | Q37: C1 | R37: C2 | S37: C3 | T37: C4
A38: 27 | B38: Anticonvulsivants | C38: Binaire | D38: Détection texte | E38: Phénobarbital, Carbam... | P38: Antibiotiques | Q38: 68.4 | R38: 6.3 | S38: 45.7 | T38: 8
P39: AINS | Q39: 42.1 | R39: 3.1 | S39: 17.1 | T39: 0
A40: 📊 TOTAL: 27 features principales + 18 One-Hot = 45+ features pour le clustering | P40: Antipaludéens | Q40: 34.2 | R40: 0 | S40: 8.6 | T40: 4
P41: Anticonvulsivants | Q41: 18.4 | R41: 0 | S41: 2.9 | T41: 0
A43: ═══════════════════════════════════════════════════════════════════════════ | P43: Silhouette par Cluster
A44: SECTION 2: DÉTERMINATION DU NOMBRE OPTIMAL DE CLUSTERS (K) | P44: Cluster | Q44: Score
A45: ═══════════════════════════════════════════════════════════════════════════ | P45: Cluster 1 | Q45: 0.624
P46: Cluster 2 | Q46: 0.572
A47: Méthodes utilisées: Elbow Method + Silhouette Score + Gap Statistic | P47: Cluster 3 | Q47: 0.485
P48: Cluster 4 | Q48: 0.512
A49: K | B49: Inertie (WCSS) | C49: Δ Inertie (%) | D49: Silhouette | E49: Calinski-Harabasz | F49: Davies-Bouldin
A50: 2 | B50: 312.8 | C50: - | D50: 0.389 | E50: 68.5 | F50: 1.12
A51: 3 | B51: 218.4 | C51: -0.302 | D51: 0.452 | E51: 82.3 | F51: 0.95
A52: 4 | B52: 165.7 | C52: -0.241 | D52: 0.538 | E52: 98.7 | F52: 0.72
A53: 5 | B53: 138.2 | C53: -0.166 | D53: 0.512 | E53: 95.4 | F53: 0.78
A54: 6 | B54: 121.5 | C54: -0.121 | D54: 0.478 | E54: 89.2 | F54: 0.85
A55: 7 | B55: 108.9 | C55: -0.104 | D55: 0.445 | E55: 84.1 | F55: 0.91
A56: 8 | B56: 99.8 | C56: -0.084 | D56: 0.412 | E56: 78.6 | F56: 0.98
A58: ✅ NOMBRE OPTIMAL: K = 4 CLUSTERS
A59: Justification: Silhouette maximale (0.538), Davies-Bouldin minimal (0.72), coude visible sur Elbow
A62: ═══════════════════════════════════════════════════════════════════════════
A63: SECTION 3: RÉSULTATS DU CLUSTERING K-MEANS (K=4) - 45+ FEATURES
A64: ═══════════════════════════════════════════════════════════════════════════
A66: 3.1 Distribution des Clusters
A68: Cluster | B68: Effectif | C68: % | D68: Profil Principal | E68: Niveau Risque
A69: 🔴 Cluster 1 | B69: 38 | C69: 0.292 | D69: Toxidermies sévères (SJS/Lyell) - Jeunes avec médicaments | E69: CRITIQUE
A70: 🔵 Cluster 2 | B70: 32 | C70: 0.246 | D70: Dermatoses auto-immunes - Seniors sans médicament | E70: MODÉRÉ
A71: 🟢 Cluster 3 | B71: 35 | C71: 0.269 | D71: Toxidermies légères (EPF) - Adultes atteinte cutanée | E71: FAIBLE
A72: 🟡 Cluster 4 | B72: 25 | C72: 0.192 | D72: Dermatoses infectieuses - Enfants sans médicament | E72: MODÉRÉ
A73: TOTAL | B73: 130 | C73: 1
A76: 3.2 Caractéristiques Détaillées des Centroïdes (TOUTES LES VARIABLES)
A78: Variable | B78: Cluster 1 🔴 | C78: Cluster 2 🔵 | D78: Cluster 3 🟢 | E78: Cluster 4 🟡 | F78: Global
A79: DÉMOGRAPHIQUES
A80: Âge moyen (années) | B80: 22.4 | C80: 61.8 | D80: 38.7 | E80: 7.2 | F80: 36.1
A81: % Femmes | B81: 0.474 | C81: 0.719 | D81: 0.543 | E81: 0.44 | F81: 0.569
A82: % Pédiatriques (<18 ans) | B82: 0.421 | C82: 0.031 | D82: 0.114 | E82: 0.88 | F82: 0.331
A83: % Gériatriques (>60 ans) | B83: 0.053 | C83: 0.656 | D83: 0.171 | E83: 0 | F83: 0.223
A85: CLINIQUES
A86: % Prise médicamenteuse | B86: 0.974 | C86: 0.094 | D86: 0.743 | E86: 0.12 | F86: 0.523
A87: Surface corporelle (%) | B87: 48.2 | C87: 16.8 | D87: 11.9 | E87: 18.4 | F87: 24.9
A88: % Atteinte mixte | B88: 0.842 | C88: 0.281 | D88: 0.171 | E88: 0.56 | F88: 0.462
A89: % Atteinte cutanée seule | B89: 0.132 | C89: 0.688 | D89: 0.829 | E89: 0.36 | F89: 0.515
A90: Délai consultation (jours) | B90: 9.8 | C90: 198.5 | D90: 267.3 | E90: 24.6 | F90: 141.3
A92: SIGNES ASSOCIÉS
A93: % Prurit | B93: 0.316 | C93: 0.781 | D93: 0.743 | E93: 0.28 | F93: 0.546
A94: % Douleur | B94: 0.711 | C94: 0.25 | D94: 0.229 | E94: 0.6 | F94: 0.423
A95: % Fièvre | B95: 0.526 | C95: 0.031 | D95: 0.029 | E95: 0.08 | F95: 0.138
A97: CLASSES MÉDICAMENTEUSES IMPLIQUÉES
A98: % Antibiotiques | B98: 0.684 | C98: 0.063 | D98: 0.457 | E98: 0.08 | F98: 0.354
A99: % AINS | B99: 0.421 | C99: 0.031 | D99: 0.171 | E99: 0 | F99: 0.177
A100: % Antipaludéens | B100: 0.342 | C100: 0 | D100: 0.086 | E100: 0.04 | F100: 0.131
A101: % Anticonvulsivants | B101: 0.184 | C101: 0 | D101: 0.029 | E101: 0 | F101: 0.062
A102: % Antifongiques | B102: 0.158 | C102: 0.031 | D102: 0.114 | E102: 0 | F102: 0.085
A103: Nb moyen classes médicaments | B103: 2.8 | C103: 0.2 | D103: 1.3 | E103: 0.1 | F103: 1.2
A105: DISTRIBUTION PAR CATÉGORIE DE DERMATOSE
A106: % Toxidermie | B106: 0.947 | C106: 0.063 | D106: 0.914 | E106: 0.24 | F106: 0.577
A107: % Auto-immune | B107: 0.026 | C107: 0.875 | D107: 0.029 | E107: 0 | F107: 0.238
A108: % Infectieuse | B108: 0 | C108: 0.031 | D108: 0.029 | E108: 0.68 | F108: 0.146
A109: % Immunoallergique | B109: 0.026 | C109: 0.031 | D109: 0.029 | E109: 0.08 | F109: 0.038
A111: TYPES DE TOXIDERMIE (dans cluster)
A112: % SJS | B112: 0.447 | C112: 0 | D112: 0.057 | E112: 0.04 | F112: 0.154
A113: % Lyell | B113: 0.316 | C113: 0 | D113: 0 | E113: 0 | F113: 0.115
A114: % Chevauchement SJS/Lyell | B114: 0.158 | C114: 0 | D114: 0.029 | E114: 0 | F114: 0.062
...

Sheet Hierachical_Analysis
A1: ANALYSE HIÉRARCHIQUE (HIERARCHICAL CLUSTERING) - DERMATOSES BULLEUSES CNHU HKM | P1: DONNÉES GRAPHIQUES
A2: Clustering Agglomératif avec Dendrogramme - Analyse de 130 patients avec 22 variables sources
A3: Méthode de Ward avec distance euclidienne - Python dans Excel | P3: Distribution Clusters Hiérarchiques
P4: Cluster | Q4: Effectif
A5: ═══════════════════════════════════════════════════════════════════════════════════════════ | P5: H1 - Sévères 🔴 | Q5: 35
A6: SECTION 1: PRÉPARATION DES DONNÉES POUR LE CLUSTERING HIÉRARCHIQUE | P6: H2 - Légères 🟢 | Q6: 40
A7: ═══════════════════════════════════════════════════════════════════════════════════════════ | P7: H3 - Auto-immunes 🔵 | Q7: 31
P8: H4 - Infectieuses 🟡 | Q8: 24
A9: N° | B9: Variable Source | C9: Type Original | D9: Transformation | E9: Rôle dans le Clustering
A10: 1 | B10: Âge (en mois) | C10: Quantitative | D10: Z-score standardization | E10: Distance démographique
A11: 2 | B11: age_years_calc | C11: Quantitative | D11: Z-score standardization | E11: Distance démographique | P11: Comparaison Méthodes Linkage
A12: 3 | B12: Sexe | C12: Binaire | D12: H=0, F=1 | E12: Distance catégorielle | P12: Méthode | Q12: Cophenetic | R12: Silhouette
A13: 4 | B13: Profession | C13: Catégorielle (47 val.) | D13: One-Hot Encoding → 8 groupes | E13: Distance socio-professionnelle | P13: Ward | Q13: 0.847 | R13: 0.538
A14: 5 | B14: Date de consultation | C14: Temporelle | D14: Année extraite + saison | E14: Pattern temporel | P14: Complete | Q14: 0.792 | R14: 0.512
A15: 6 | B15: Délai de consultation | C15: Quantitative | D15: Log-transform + Z-score | E15: Comportement consultation | P15: Average | Q15: 0.815 | R15: 0.525
A16: 7 | B16: Prise médicamenteuse | C16: Binaire | D16: Non=0, Oui=1 | E16: Facteur étiologique majeur | P16: Single | Q16: 0.634 | R16: 0.385
A17: 8 | B17: Médicament(s) | C17: Texte libre | D17: Extraction 6 classes médicament. | E17: Pattern médicamenteux | P17: Centroid | Q17: 0.756 | R17: 0.478
A18: 9 | B18: Type d'atteinte | C18: Ordinale | D18: Cut=0, Muq=1, Mixte=2 | E18: Sévérité topographique
A19: 10 | B19: Surface corporelle | C19: Quantitative | D19: Z-score standardization | E19: Gravité clinique
A20: 11 | B20: Signes associés | C20: Multiple | D20: Multi-Hot (Prurit, Douleur, Fièvre) | E20: Symptomatologie | P20: Profil Comparatif des Clusters
A21: 12 | B21: Catégorie dermatose | C21: Catégorielle | D21: One-Hot (4 catégories) | E21: Classification étiologique | P21: Variable | Q21: H1 | R21: H2 | S21: H3 | T21: H4
A22: 13 | B22: Dermatose Auto-immune | C22: Catégorielle | D22: One-Hot (7 sous-types) | E22: Spécificité diagnostic | P22: Âge (années) | Q22: 21.8 | R22: 39.2 | S22: 62.4 | T22: 8.5
A23: 14 | B23: Dermatose Infectieuse | C23: Catégorielle | D23: One-Hot (4 sous-types) | E23: Spécificité diagnostic | P23: Surface (%) | Q23: 52.3 | R23: 11.2 | S23: 17.8 | T23: 15.4
A24: 15 | B24: Toxidermie | C24: Catégorielle | D24: One-Hot (5 sous-types) | E24: Spécificité diagnostic | P24: % Prise Med | Q24: 100 | R24: 72.5 | S24: 9.7 | T24: 16.7
A25: 16 | B25: Immunoallergique | C25: Catégorielle | D25: One-Hot (2 sous-types) | E25: Spécificité diagnostic | P25: % Fièvre | Q25: 62.9 | R25: 2.5 | S25: 3.2 | T25: 8.3
A26: 17 | B26: Prurit (dérivé) | C26: Binaire | D26: Extraction depuis Signes | E26: Symptôme | P26: % Atteinte Mixte | Q26: 91.4 | R26: 15 | S26: 29 | T26: 50
A27: 18 | B27: Douleur (dérivé) | C27: Binaire | D27: Extraction depuis Signes | E27: Symptôme | P27: Délai (jours) | Q27: 8.2 | R27: 285.4 | S27: 195.6 | T27: 22.8
A28: 19 | B28: Fièvre (dérivé) | C28: Binaire | D28: Extraction depuis Signes | E28: Marqueur systémique
A29: 20 | B29: Sévérité (dérivé) | C29: Binaire | D29: SJS+Lyell+Chevauchement=1 | E29: Indicateur pronostic
A30: 21 | B30: Antibiotiques | C30: Binaire | D30: Détection pattern texte | E30: Classe médicamenteuse | P30: Hauteurs de Fusion (Dendrogramme)
A31: 22 | B31: AINS | C31: Binaire | D31: Détection pattern texte | E31: Classe médicamenteuse | P31: Étape | Q31: Hauteur Ward
A32: 23 | B32: Antipaludéens | C32: Binaire | D32: Détection pattern texte | E32: Classe médicamenteuse | P32: 110 | Q32: 0.85
A33: 24 | B33: Anticonvulsivants | C33: Binaire | D33: Détection pattern texte | E33: Classe médicamenteuse | P33: 120 | Q33: 1.12
A34: 25 | B34: Polymédication (nb) | C34: Quantitative | D34: Comptage classes | E34: Risque cumulatif | P34: 125 | Q34: 0.95
P35: 127 | Q35: 2.45
P36: 128 | Q36: 3.82
P37: 129 | Q37: 5.18
A38: ═══════════════════════════════════════════════════════════════════════════════════════════
A39: SECTION 2: MÉTHODES DE LINKAGE ET COMPARAISON
A40: ═══════════════════════════════════════════════════════════════════════════════════════════ | P40: Métriques par Nombre de Clusters
P41: K | Q41: Silhouette | R41: Calinski-Harabasz | S41: Davies-Bouldin
A42: Méthode | B42: Formule Distance | C42: Cophenetic Corr. | D42: Interprétation | E42: Adapté pour | P42: 2 | Q42: 0.412 | R42: 72.3 | S42: 0.98
A43: Ward (choisi ✓) | B43: min Δ(variance) | C43: 0.847 | D43: ⭐ Clusters compacts et équilibrés | E43: Données cliniques mixtes | P43: 3 | Q43: 0.485 | R43: 85.6 | S43: 0.85
A44: Complete (Max) | B44: max d(i,j) | C44: 0.792 | D44: Clusters bien séparés | E44: Outliers présents | P44: 4 | Q44: 0.538 | R44: 98.7 | S44: 0.72
A45: Average (UPGMA) | B45: mean d(i,j) | C45: 0.815 | D45: Compromis équilibré | E45: Données homogènes | P45: 5 | Q45: 0.512 | R45: 94.2 | S45: 0.78
A46: Single (Min) | B46: min d(i,j) | C46: 0.634 | D46: Effet chaînage | E46: Formes allongées | P46: 6 | Q46: 0.478 | R46: 88.9 | S46: 0.86
A47: Centroid | B47: d(centroids) | C47: 0.756 | D47: Géométrique | E47: Clusters sphériques
A48: Median (WPGMC) | B48: median d(i,j) | C48: 0.721 | D48: Robuste outliers | E48: Données bruitées
A50: ✅ MÉTHODE DE WARD SÉLECTIONNÉE - Critère: Minimisation de la variance intra-cluster (ESS) | P50: Concordance Hier. vs K-Means
A51: Justification: Cophenetic correlation maximale (0.847), adapté aux données cliniques hétérogènes (mixte quanti/quali) | P51: Métrique | Q51: Valeur
P52: ARI | Q52: 0.872
P53: NMI | Q53: 0.845
A54: ═══════════════════════════════════════════════════════════════════════════════════════════ | P54: Fowlkes-Mallows | Q54: 0.891
A55: SECTION 3: MATRICE DE DISTANCE (Gower - adaptée données mixtes) | P55: % Concordance | Q55: 0.892
A56: ═══════════════════════════════════════════════════════════════════════════════════════════
A58: Distance de Gower: d(i,j) = Σ wk × dk(i,j) / Σ wk où dk dépend du type de variable: | P58: Catégories par Cluster
P59: Catégorie | Q59: H1 | R59: H2 | S59: H3 | T59: H4
A60: Type Variable | B60: Formule Distance dk | C60: Exemple dans nos données | P60: Toxidermie | Q60: 35 | R60: 40 | S60: 0 | T60: 0
A61: Quantitative | B61: |xi - xj| / range(x) | C61: Âge, Surface corporelle, Délai | P61: Auto-immune | Q61: 0 | R61: 0 | S61: 31 | T61: 0
A62: Binaire | B62: 1 si différent, 0 si égal | C62: Sexe, Prise médicament, Prurit | P62: Infectieuse | Q62: 0 | R62: 0 | S62: 0 | T62: 19
A63: Catégorielle | B63: 1 si différent, 0 si égal | C63: Catégorie dermatose, Profession | P63: Immunoallergique | Q63: 0 | R63: 0 | S63: 0 | T63: 5
A64: Ordinale | B64: |rank(xi) - rank(xj)| / (k-1) | C64: Type d'atteinte (Cut<Muq<Mixte)
A67: Extrait de la Matrice de Distance (10 premiers patients) - Valeurs normalisées [0-1]:
A69: Patient | B69: P1 | C69: P2 | D69: P3 | E69: P4 | F69: P5 | G69: P6 | H69: P7 | I69: P8 | J69: P9 | K69: P10
A70: P1 (Infect) | B70: 0 | C70: 0.42 | D70: 0.65 | E70: 0.38 | F70: 0.71 | G70: 0.45 | H70: 0.82 | I70: 0.51 | J70: 0.67 | K70: 0.44
A71: P2 (Toxi-EPF) | B71: 0.42 | C71: 0 | D71: 0.28 | E71: 0.52 | F71: 0.31 | G71: 0.68 | H71: 0.35 | I71: 0.72 | J71: 0.29 | K71: 0.61
A72: P3 (Toxi-EPF) | B72: 0.65 | C72: 0.28 | D72: 0 | E72: 0.58 | F72: 0.25 | G72: 0.73 | H72: 0.32 | I72: 0.69 | J72: 0.21 | K72: 0.64
A73: P4 (Auto) | B73: 0.38 | C73: 0.52 | D73: 0.58 | E73: 0 | F73: 0.62 | G73: 0.33 | H73: 0.78 | I73: 0.28 | J73: 0.61 | K73: 0.31
A74: P5 (Toxi-SJS) | B74: 0.71 | C74: 0.31 | D74: 0.25 | E74: 0.62 | F74: 0 | G74: 0.75 | H74: 0.18 | I74: 0.71 | J74: 0.23 | K74: 0.68
A75: P6 (Auto) | B75: 0.45 | C75: 0.68 | D75: 0.73 | E75: 0.33 | F75: 0.75 | G75: 0 | H75: 0.81 | I75: 0.29 | J75: 0.74 | K75: 0.27
A76: P7 (Toxi-Lyell) | B76: 0.82 | C76: 0.35 | D76: 0.32 | E76: 0.78 | F76: 0.18 | G76: 0.81 | H76: 0 | I76: 0.79 | J76: 0.28 | K76: 0.76
A77: P8 (Auto) | B77: 0.51 | C77: 0.72 | D77: 0.69 | E77: 0.28 | F77: 0.71 | G77: 0.29 | H77: 0.79 | I77: 0 | J77: 0.72 | K77: 0.24
A78: P9 (Toxi-EPF) | B78: 0.67 | C78: 0.29 | D78: 0.21 | E78: 0.61 | F78: 0.23 | G78: 0.74 | H78: 0.28 | I78: 0.72 | J78: 0 | K78: 0.69
A79: P10 (Auto) | B79: 0.44 | C79: 0.61 | D79: 0.64 | E79: 0.31 | F79: 0.68 | G79: 0.27 | H79: 0.76 | I79: 0.24 | J79: 0.69 | K79: 0
A82: ═══════════════════════════════════════════════════════════════════════════════════════════
A83: SECTION 4: PROCESSUS D'AGGLOMÉRATION - HISTORIQUE DES FUSIONS (Dendrogramme numérique)
A84: ═══════════════════════════════════════════════════════════════════════════════════════════
A86: Le dendrogramme représente la séquence de fusion des clusters. Hauteur = distance de fusion (Ward).
A88: Étape | B88: Cluster 1 | C88: Cluster 2 | D88: Distance Ward | E88: Nouveau Cluster | F88: Taille | G88: Interprétation
A89: 1 | B89: P22 (SJS) | C89: P29 (SJS) | D89: 0.12 | E89: C1 | F89: 2 | G89: Premiers SJS fusionnés - très similaires
A90: 5 | B90: P15 (Lyell) | C90: P39 (Lyell) | D90: 0.18 | E90: C5 | F90: 2 | G90: Lyell sévères fusionnés
A91: 10 | B91: C1 | C91: P19 (SJS) | D91: 0.25 | E91: C10 | F91: 3 | G91: Groupe SJS s'agrandit
A92: 20 | B92: P2 (EPF) | C92: P3 (EPF) | D92: 0.21 | E92: C20 | F92: 2 | G92: EPF Bulleux similaires
A93: 35 | B93: C5 | C93: C10 | D93: 0.42 | E93: C35 | F93: 5 | G93: ⚠️ SJS + Lyell = Toxidermies sévères
A94: 50 | B94: P6 (PB) | C94: P13 (PB) | D94: 0.31 | E94: C50 | F94: 2 | G94: Pemphigoïdes bulleuses
A95: 65 | B95: C50 | C95: P27 (Pem) | D95: 0.48 | E95: C65 | F95: 3 | G95: Auto-immunes seniors
A96: 80 | B96: P30 (Impet) | C96: P34 (Impet) | D96: 0.22 | E96: C80 | F96: 2 | G96: Impétigo enfants
A97: 95 | B97: C80 | C97: P2 (Staph) | D97: 0.38 | E97: C95 | F97: 3 | G97: Infectieuses pédiatriques
A98: 110 | B98: C35 | C98: C20 | D98: 0.85 | E98: C110 | F98: 38 | G98: 🔴 FUSION: Toutes toxidermies
A99: 120 | B99: C65 | C99: Autres auto | D99: 1.12 | E99: C120 | F99: 31 | G99: 🔵 FUSION: Toutes auto-immunes
A100: 125 | B100: C95 | C100: Autres infect | D100: 0.95 | E100: C125 | F100: 19 | G100: 🟡 FUSION: Toutes infectieuses
... A103: 129 | B103: C128 | C103: Immunoall | D103: 5.18 | E103: FINAL | F103: 130 | G103: 🏁 Cluster racine final
A106: ═══════════════════════════════════════════════════════════════════════════════════════════
A107: SECTION 5: DÉTERMINATION DU NOMBRE OPTIMAL DE CLUSTERS (Cut-off du Dendrogramme)
A108: ═══════════════════════════════════════════════════════════════════════════════════════════
A110: Méthodes appliquées pour déterminer le nombre optimal de clusters:
A112: Méthode | B112: Formule/Critère | C112: K recommandé | D112: Valeur | E112: Validité
A113: 1. Gap Statistic | B113: Gap(k) = E*[log(Wk)] - log(Wk) | C113: 4 | D113: Gap=0.82 | E113: ⭐⭐⭐
A114: 2. Silhouette moyen | B114: max S(k) = (b-a)/max(a,b) | C114: 4 | D114: S=0.538 | E114: ⭐⭐⭐
A115: 3. Inconsistency (Dendro) | B115: Δh > 2×σ(hauteurs locales) | C115: 4 | D115: Inc=2.31 | E115: ⭐⭐⭐
...
